verilog/decoder/sinwave.v
module sinwave (
    input  wire [6:0] addr,
    output reg signed [15:0] sample
);
    always @(*) begin
        case (addr)
7'd0: sample = 16'sd0;
7'd1: sample = 16'sd25015;
7'd2: sample = 16'sd24270;
7'd3: sample = 16'sd5298;
7'd4: sample = -16'sd4141;
7'd5: sample = 16'sd4015;
7'd6: sample = 16'sd8528;
7'd7: sample = -16'sd7375;
7'd8: sample = -16'sd28353;
7'd9: sample = -16'sd26272;
7'd10: sample = 16'sd222;
7'd11: sample = 16'sd22232;
7'd12: sample = 16'sd18749;
7'd13: sample = 16'sd2992;
7'd14: sample = 16'sd581;
7'd15: sample = 16'sd11803;
7'd16: sample = 16'sd12320;
7'd17: sample = -16'sd9083;
7'd18: sample = -16'sd30747;
7'd19: sample = -16'sd25945;
7'd20: sample = 16'sd404;
7'd21: sample = 16'sd18077;
7'd22: sample = 16'sd12129;
7'd23: sample = 16'sd608;
7'd24: sample = 16'sd5359;
7'd25: sample = 16'sd18880;
7'd26: sample = 16'sd15303;
7'd27: sample = -16'sd10298;
7'd28: sample = -16'sd31299;
7'd29: sample = -16'sd24068;
7'd30: sample = 16'sd509;
7'd31: sample = 16'sd12788;
7'd32: sample = 16'sd4814;
7'd33: sample = -16'sd1706;
7'd34: sample = 16'sd9900;
7'd35: sample = 16'sd24822;
7'd36: sample = 16'sd17313;
7'd37: sample = -16'sd10922;
7'd38: sample = -16'sd29968;
7'd39: sample = -16'sd20771;
7'd40: sample = 16'sd509;
7'd41: sample = 16'sd6675;
7'd42: sample = -16'sd2754;
7'd43: sample = -16'sd3812;
7'd44: sample = 16'sd13923;
7'd45: sample = 16'sd29269;
7'd46: sample = 16'sd18249;
7'd47: sample = -16'sd10894;
7'd48: sample = -16'sd26826;
7'd49: sample = -16'sd16266;
7'd50: sample = 16'sd385;
7'd51: sample = 16'sd99;
7'd52: sample = -16'sd10119;
7'd53: sample = -16'sd5592;
7'd54: sample = 16'sd17173;
7'd55: sample = 16'sd31956;
7'd56: sample = 16'sd18077;
7'd57: sample = -16'sd10189;
7'd58: sample = -16'sd22055;
7'd59: sample = -16'sd10836;
7'd60: sample = 16'sd133;
7'd61: sample = -16'sd6544;
7'd62: sample = -16'sd16840;
7'd63: sample = -16'sd6953;
7'd64: sample = 16'sd19437;
7'd65: sample = 16'sd32721;
7'd66: sample = 16'sd16829;
7'd67: sample = -16'sd8826;
7'd68: sample = -16'sd15938;
7'd69: sample = -16'sd4819;
7'd70: sample = -16'sd238;
7'd71: sample = -16'sd12855;
7'd72: sample = -16'sd22516;
7'd73: sample = -16'sd7830;
7'd74: sample = 16'sd20559;
7'd75: sample = 16'sd31519;
7'd76: sample = 16'sd14603;
7'd77: sample = -16'sd6864;
7'd78: sample = -16'sd8837;
7'd79: sample = 16'sd1420;
7'd80: sample = -16'sd705;
7'd81: sample = -16'sd18446;
7'd82: sample = -16'sd26812;
7'd83: sample = -16'sd8193;
7'd84: sample = 16'sd20452;
7'd85: sample = 16'sd28425;
7'd86: sample = 16'sd11553;
7'd87: sample = -16'sd4405;
7'd88: sample = -16'sd1177;
7'd89: sample = 16'sd7503;
7'd90: sample = -16'sd1232;
7'd91: sample = -16'sd22974;
7'd92: sample = -16'sd29477;
7'd93: sample = -16'sd8048;
7'd94: sample = 16'sd19100;
7'd95: sample = 16'sd23626;
7'd96: sample = 16'sd7879;
7'd97: sample = -16'sd1585;
7'd98: sample = 16'sd6581;
7'd99: sample = 16'sd13068;
7'd100: sample = -16'sd1774;
7'd101: sample = -16'sd26154;
7'd102: sample = -16'sd30360;
7'd103: sample = -16'sd7428;
7'd104: sample = 16'sd16565;
7'd105: sample = 16'sd17411;
7'd106: sample = 16'sd3817;
7'd107: sample = 16'sd1433;
7'd108: sample = 16'sd13970;
7'd109: sample = 16'sd17785;
7'd110: sample = -16'sd2280;
7'd111: sample = -16'sd27782;
7'd112: sample = -16'sd29418;
7'd113: sample = -16'sd6396;
7'd114: sample = 16'sd12981;
7'd115: sample = 16'sd10157;
7'd116: sample = -16'sd383;
7'd117: sample = 16'sd4467;
7'd118: sample = 16'sd20543;
7'd119: sample = 16'sd21383;
7'd120: sample = -16'sd2697;
7'd121: sample = -16'sd27746;
7'd122: sample = -16'sd26718;
7'd123: sample = -16'sd5040;
7'd124: sample = 16'sd8550;
7'd125: sample = 16'sd2301;
7'd126: sample = -16'sd4465;
7'd127: sample = 16'sd7329;


            default: sample = 16'sd0;
        endcase
    end
endmodule

verilog/decoder/goertzel.v
module goertzel
  (

    input wire clk,reset,
    output reg signed [15:0] maxcoeff,
    output wire signed [15:0] COEFF_tb,
    output reg signed [63:0] power_tb,
    output reg signed [63:0] max_power,
    output wire signed [63:0] power



  );

  reg [6:0] addr = 7'd0;
  wire signed [15:0] sample;

  localparam integer Fs = 8000;
  localparam integer N  = 128;

  reg signed [15:0] COEFF [0:7];




  initial
  begin
    COEFF[0] = 16'sd28106; // 697 Hz
    COEFF[1] = 16'sd27018; // 770 Hz
    COEFF[2] = 16'sd25330; // 852 Hz
    COEFF[3] = 16'sd24126; // 941 Hz
    // COEFF[4] = 16'sd19478; // 1209 Hz
    // COEFF[5] = 16'sd16846; // 1336 Hz
    // COEFF[6] = 16'sd12490; // 1477 Hz
    // COEFF[7] = 16'sd9220;  // 1633 Hz
  end



  reg [1:0] i = 2'd0;
  reg signed [31:0] s1 = 0;
  reg signed [31:0] s2 = 0;

  wire signed [31:0] s_next;
  wire signed [47:0] s1_prod;
  assign s1_prod = COEFF[i] * s1;
  reg [6:0] count = 0;

  assign COEFF_tb=COEFF[i];
  assign s_next = {{16{sample[15]}}, sample} + (s1_prod >>> 14) - s2;

  assign power =
         (s_next * s_next)
         + (s1 * s1)
         - (((COEFF[i] * s_next * s1) >>> 14));

  always @(posedge clk)
  begin

    if(reset)
    begin
      addr      <= 7'd0;
      count     <= 7'd0;
      i         <= 2'd0;
      s1        <= 32'sd0;
      s2        <= 32'sd0;
      max_power <= 64'sd0;
      maxcoeff  <= 16'sd0;
      power_tb  <= 64'sd0;

    end
    else
    begin


      addr <= addr + 1'b1;

      if(count == 7'd127)
      begin
        power_tb<=power;

        if(power>max_power)
        begin
          max_power<=power;
          maxcoeff<=COEFF[i];

        end


        count <= 7'd0;
        s1    <= 32'sd0;
        s2    <= 32'sd0;
        addr  <= 7'd0;

        if (i == 2'd3)
        begin
          i <= 2'd0;
        end
        else
        begin
          i <= i + 1'b1;
        end
      end
      else
      begin

        s2 <= s1;
        s1 <= s_next;

        count <= count + 1'b1;

      end
    end
  end

  sinwave sw(
            .addr(addr),
            .sample(sample)
          );

endmodule

module goertzel1
  (

    input wire clk,reset,
    output reg signed [15:0] maxcoeff,
    output wire signed [15:0] COEFF_tb,
    output reg signed [63:0] power_tb,
    output reg signed [63:0] max_power,
    output wire signed [63:0] power



  );

  reg [6:0] addr = 7'd0;
  wire signed [15:0] sample;

  localparam integer Fs = 8000;
  localparam integer N  = 128;

  reg signed [15:0] COEFF [0:7];




  initial
  begin
    // COEFF[0] = 16'sd28106; // 697 Hz
    // COEFF[1] = 16'sd27018; // 770 Hz
    // COEFF[2] = 16'sd25330; // 852 Hz
    // COEFF[3] = 16'sd24126; // 941 Hz
    COEFF[0] = 16'sd19478; // 1209 Hz
    COEFF[1] = 16'sd16846; // 1336 Hz
    COEFF[2] = 16'sd12490; // 1477 Hz
    COEFF[3] = 16'sd9220;  // 1633 Hz
  end



  reg [1:0] i = 2'd0;
  reg signed [31:0] s1 = 0;
  reg signed [31:0] s2 = 0;

  wire signed [31:0] s_next;
  wire signed [47:0] s1_prod;
  assign s1_prod = COEFF[i] * s1;
  reg [6:0] count = 0;

  assign COEFF_tb=COEFF[i];
  assign s_next = {{16{sample[15]}}, sample} + (s1_prod >>> 14) - s2;

  assign power =
         (s_next * s_next)
         + (s1 * s1)
         - (((COEFF[i] * s_next * s1) >>> 14));

  always @(posedge clk)
  begin

    if(reset)
    begin
      addr      <= 7'd0;
      count     <= 7'd0;
      i         <= 2'd0;
      s1        <= 32'sd0;
      s2        <= 32'sd0;
      max_power <= 64'sd0;
      maxcoeff  <= 16'sd0;
      power_tb  <= 64'sd0;

    end
    else
    begin


      addr <= addr + 1'b1;

      if(count == 7'd127)
      begin
        power_tb<=power;

        if(power>max_power)
        begin
          max_power<=power;
          maxcoeff<=COEFF[i];

        end


        count <= 7'd0;
        s1    <= 32'sd0;
        s2    <= 32'sd0;
        addr  <= 7'd0;

        if (i == 2'd3)
        begin
          i <= 2'd0;
        end
        else
        begin
          i <= i + 1'b1;
        end
      end
      else
      begin

        s2 <= s1;
        s1 <= s_next;

        count <= count + 1'b1;

      end
    end
  end

  sinwave sw(
            .addr(addr),
            .sample(sample)
          );

endmodule

verilog/decoder/testbench.v
`timescale 1ns/1ps

module tb_goertzel;

reg clk;
reg reset;



reg [7:0] key [0:3][0:3];
integer j,k;

initial begin
    key[0][0] = "1"; key[0][1] = "2"; key[0][2] = "3"; key[0][3] = "A";
    key[1][0] = "4"; key[1][1] = "5"; key[1][2] = "6"; key[1][3] = "B";
    key[2][0] = "7"; key[2][1] = "8"; key[2][2] = "9"; key[2][3] = "C";
    key[3][0] = "*"; key[3][1] = "0"; key[3][2] = "#"; key[3][3] = "D";
end

wire signed [15:0] maxcoeff;
    wire signed [63:0] power ;
    wire signed [63:0] power_tb ;
    wire signed [63:0] max_power ;
    wire signed [15:0] COEFF_tb;


reg reset1;


wire signed [15:0] maxcoeff1;
    wire signed [63:0] power1 ;
    wire signed [63:0] power_tb1 ;
    wire signed [63:0] max_power1 ;
    wire signed [15:0] COEFF_tb1;

goertzel dut(
.clk(clk),
.reset(reset),
.maxcoeff(maxcoeff),
.power(power),
.power_tb(power_tb),
.COEFF_tb(COEFF_tb),
.max_power(max_power)

);

goertzel1 dut1(
.clk(clk),
.reset(reset1),
.maxcoeff(maxcoeff1),
.power(power1),
.power_tb(power_tb1),
.COEFF_tb(COEFF_tb1),
.max_power(max_power1)

);



always #41.667 clk = ~clk;

integer F;

initial begin
    $dumpfile("wave.vcd");
    $dumpvars(0, tb_goertzel);
        clk = 0;
    reset=1;
    #100
    reset=0;
          $monitor("time=%0t , i=%0d , coeff=%0d , power=%0d , peakpower=%0d", 
                $time, dut.i, COEFF_tb, power_tb, max_power);
   #50000;  
case(maxcoeff) 
    16'sd28106 :begin
        F = 697;
        j=0;
    end
    16'sd27018 : begin
        F = 770; 
        j=1;
    end
    16'sd25330 : begin
        F = 852;
        j=2;
    end
    16'sd24126 : 
    begin
    F = 941; 
    j=3;
    end
    // 16'sd19478 : F = 1209; 
    // 16'sd16846 : F = 1336; 
    // 16'sd12490 : F = 1477; 
    // 16'sd9220  : F = 1633;
    default    : F = 0;
endcase

        $display("det freq: %0d Hz", F);
        $display("power peak: %0d", max_power);
        


           clk = 0;
    reset1=1;
    #100
    reset1=0;
          $monitor("time=%0t , i=%0d , coeff=%0d , power=%0d , peakpower=%0d", 
                $time, dut1.i, COEFF_tb1, power_tb1, max_power1);
   #50000;  
case(maxcoeff1) 
    // 16'sd28106 : F = 697;
    // 16'sd27018 : F = 770; 
    // 16'sd25330 : F = 852;
    // 16'sd24126 : F = 941; 
    16'sd19478 : begin 
        F = 1209;
        k=0;
    end 

    16'sd16846 : begin
        F = 1336; 
        k=1;
    end
    16'sd12490 :begin
        F = 1477;
        k=2;
    end 
    16'sd9220  :begin
      
  F = 1633;
k=3;
end 
    default    : F = 0;
endcase

        $display("det freq: %0d Hz", F);
        $display("power peak: %0d", max_power1);

$display("key is: %0s", key[j][k]);






        $finish;
    
end





endmodule

verilog/decoder/wave.vcd
$date
	Mon Jun 29 15:08:25 2026
$end
$version
	Icarus Verilog
$end
$timescale
	1ps
$end
$scope module tb_goertzel $end
$var wire 64 ! power_tb1 [63:0] $end
$var wire 64 " power_tb [63:0] $end
$var wire 64 # power1 [63:0] $end
$var wire 64 $ power [63:0] $end
$var wire 16 % maxcoeff1 [15:0] $end
$var wire 16 & maxcoeff [15:0] $end
$var wire 64 ' max_power1 [63:0] $end
$var wire 64 ( max_power [63:0] $end
$var wire 16 ) COEFF_tb1 [15:0] $end
$var wire 16 * COEFF_tb [15:0] $end
$var reg 1 + clk $end
$var reg 1 , reset $end
$var reg 1 - reset1 $end
$var integer 32 . F [31:0] $end
$var integer 32 / j [31:0] $end
$var integer 32 0 k [31:0] $end
$scope module dut $end
$var wire 16 1 COEFF_tb [15:0] $end
$var wire 1 + clk $end
$var wire 1 , reset $end
$var wire 16 2 sample [15:0] $end
$var wire 32 3 s_next [31:0] $end
$var wire 48 4 s1_prod [47:0] $end
$var wire 64 5 power [63:0] $end
$var reg 7 6 addr [6:0] $end
$var reg 7 7 count [6:0] $end
$var reg 2 8 i [1:0] $end
$var reg 64 9 max_power [63:0] $end
$var reg 16 : maxcoeff [15:0] $end
$var reg 64 ; power_tb [63:0] $end
$var reg 32 < s1 [31:0] $end
$var reg 32 = s2 [31:0] $end
$scope module sw $end
$var wire 7 > addr [6:0] $end
$var reg 16 ? sample [15:0] $end
$upscope $end
$upscope $end
$scope module dut1 $end
$var wire 16 @ COEFF_tb [15:0] $end
$var wire 1 + clk $end
$var wire 1 - reset $end
$var wire 16 A sample [15:0] $end
$var wire 32 B s_next [31:0] $end
$var wire 48 C s1_prod [47:0] $end
$var wire 64 D power [63:0] $end
$var reg 7 E addr [6:0] $end
$var reg 7 F count [6:0] $end
$var reg 2 G i [1:0] $end
$var reg 64 H max_power [63:0] $end
$var reg 16 I maxcoeff [15:0] $end
$var reg 64 J power_tb [63:0] $end
$var reg 32 K s1 [31:0] $end
$var reg 32 L s2 [31:0] $end
$scope module sw $end
$var wire 7 M addr [6:0] $end
$var reg 16 N sample [15:0] $end
$upscope $end
$upscope $end
$upscope $end
$enddefinitions $end
#0
$dumpvars
b0 N
b0 M
b0 L
b0 K
bx J
bx I
bx H
b0 G
b0 F
b0 E
b0 D
b0 C
b0 B
b0 A
b100110000010110 @
b0 ?
b0 >
b0 =
b0 <
bx ;
bx :
bx 9
b0 8
b0 7
b0 6
b0 5
b0 4
b0 3
b0 2
b110110111001010 1
bx 0
bx /
bx .
x-
1,
0+
b110110111001010 *
b100110000010110 )
bx (
bx '
bx &
bx %
b0 $
b0 #
bx "
bx !
$end
#41667
b100101010011000011000011010001 #
b100101010011000011000011010001 D
b110000110110111 B
b110000110110111 A
b110000110110111 N
b0 "
b0 ;
b0 &
b0 :
b0 (
b0 9
b1 F
b1 E
b1 M
1+
#83334
0+
#100000
0,
#125001
b1101001011111000 B
b100101010011000011000011010001 $
b100101010011000011000011010001 5
b110000110110111 3
b101111011001110 A
b101111011001110 N
b110000110110111 2
b110000110110111 ?
b10 F
b11101000010101011100110111010 C
b1110011011011000100011000010111 #
b1110011011011000100011000010111 D
b110000110110111 K
b10 E
b10 M
b1 7
b1 6
b1 >
1+
#166668
0+
#208335
b10000011001101110 3
b101111011001110 2
b101111011001110 ?
b1010110111001010 B
b1010010110010 A
b1010010110010 N
b10 7
b101001111010000000010101100110 4
b10000110011110111010101100110011 $
b10000110011110111010101100110011 5
b110000110110111 <
b10 6
b10 >
b11 F
b111110101100111100000101010000 C
b1111001100100101010010110111110 #
b1111001100100101010010110111110 D
b1101001011111000 K
b110000110110111 L
b11 E
b11 M
1+
#250002
0+
#291669
b11111111111111111110101101110110 B
b1110111111010011 A
b1110111111010011 N
b10111010100101010 3
b1010010110010 2
b1010010110010 ?
b100 F
b110011101001101110011101011100 C
b10001000001101000000010111111000 #
b10001000001101000000010111111000 D
b1010110111001010 K
b1101001011111000 L
b100 E
b100 M
b11 7
b1110000100010111110100011001100 4
b10011100101111110111110110010011 $
b10011100101111110111110110010011 5
b10000011001101110 <
b110000110110111 =
b11 6
b11 >
1+
#333336
0+
#375003
b10110100110001010 3
b1110111111010011 2
b1110111111010011 ?
b11111111111111110100100101111010 B
b111110101111 A
b111110101111 N
b100 7
b10100000000010010101010100100100 4
b10010110011111000011000011101010 $
b10010110011111000011000011101010 5
b10111010100101010 <
b10000011001101110 =
b100 6
b100 >
b101 F
b111111111111111111111001111001010100010000100100 C
b1110010010111111101101001010110 #
b1110010010111111101101001010110 D
b11111111111111111110101101110110 K
b1010110111001010 L
b101 E
b101 M
1+
#416670
0+
#458337
b11111111111111110101110011011100 B
b10000101010000 A
b10000101010000 N
b10000011010111001 3
b111110101111 2
b111110101111 ?
b110 F
b111111111111111111001001110000001000100001111100 C
b1011111110100011000001100011101 #
b1011111110100011000001100011101 D
b11111111111111110100100101111010 K
b11111111111111111110101101110110 L
b110 E
b110 M
b101 7
b10011011000011010000100011100100 4
b10001111101110000010001000000010 $
b10001111101110000010001000000010 5
b10110100110001010 <
b10111010100101010 =
b101 6
b101 >
1+
#500004
0+
#541671
b111101001110110 3
b10000101010000 2
b10000101010000 ?
b11111111111111111101011111000100 B
b1110001100110001 A
b1110001100110001 N
b110 7
b1110000101011000001001011111010 4
b1110000100111000001111010100110 $
b1110000100111000001111010100110 5
b10000011010111001 <
b10110100110001010 =
b110 6
b110 >
b111 F
b111111111111111111001111100000110100101011101000 C
b1001111110011100100010100001000 #
b1001111110011100100010100001000 D
b11111111111111110101110011011100 K
b11111111111111110100100101111010 L
b111 E
b111 M
1+
#583338
0+
#625005
b10010001101 B
b1001000100111111 A
b1001000100111111 N
b11111111111111111010111010001011 3
b1110001100110001 2
b1110001100110001 ?
b1000 F
b111111111111111111110100000010101011101011011000 C
b111010000010011000001101000 #
b111010000010011000001101000 D
b11111111111111111101011111000100 K
b11111111111111110101110011011100 L
b1000 E
b1000 M
b111 7
b110100100001001101111100011100 4
b10010111010110000001101100100101 $
b10010111010110000001101100100101 5
b111101001110110 <
b10000011010111001 =
b111 6
b111 >
1+
#666672
0+
#708339
b11111111111111101000101100001100 3
b1001000100111111 2
b1001000100111111 ?
b11111111111111111100011100000101 B
b1001100101100000 A
b1001100101100000 N
b1000 7
b111111111111111111011101000100001110100010101110 4
b101101101101011100110000011110100 $
b101101101101011100110000011110100 5
b11111111111111111010111010001011 <
b111101001110110 =
b1000 6
b1000 >
b1001 F
b1010110100100000000011110 C
b1101111101111100000111010000 #
b1101111101111100000111010000 D
b10010001101 K
b11111111111111111101011111000100 L
b1001 E
b1001 M
1+
#750006
0+
#791673
b11111111111111111011100010010011 B
b11011110 A
b11011110 N
b11111111111111010110101100001100 3
b1001100101100000 2
b1001100101100000 ?
b1010 F
b111111111111111111101111000100001001011001101110 C
b1101101101011111100110100101 #
b1101101101011111100110100101 D
b11111111111111111100011100000101 K
b10010001101 L
b1010 E
b1010 M
b1001 7
b111111111111111101100000000011011101001101111000 4
b1001010101111111011101101010011100 $
b1001010101111111011101101010011100 5
b11111111111111101000101100001100 <
b11111111111111111010111010001011 =
b1001 6
b1001 >
1+
#833340
0+
#875007
b11111111111111010000011111111100 3
b11011110 2
b11011110 ?
b11101011101001 B
b101011011011000 A
b101011011011000 N
b1010 7
b111111111111111011100100100010101001001101111000 4
b1001010100101011101010100001111011 $
b1001010100101011101010100001111011 5
b11111111111111010110101100001100 <
b11111111111111101000101100001100 =
b1010 6
b1010 >
b1011 F
b111111111111111111101010110001011000000010100010 C
b110101000001100101100011011111 #
b110101000001100101100011011111 D
b11111111111111111011100010010011 K
b11111111111111111100011100000101 L
b1011 E
b1011 M
1+
#916674
0+
#958341
b1101011010110010 B
b100100100111101 A
b100100100111101 N
b11111111111111011101010000000110 3
b101011011011000 2
b101011011011000 ?
b1100 F
b10001100000100011110000000110 C
b10000110111000000101000011101010 #
b10000110111000000101000011101010 D
b11101011101001 K
b11111111111111111011100010010011 L
b1100 E
b1100 M
b1011 7
b111111111111111010111010000011101001100011011000 4
b1001111000010010110000111010101011 $
b1001111000010010110000111010101011 5
b11111111111111010000011111111100 <
b11111111111111010110101100001100 =
b1011 6
b1011 >
1+
#1000008
0+
#1041675
b11111111111111111000011110000000 3
b100100100111101 2
b100100100111101 ?
b1101000000000100 B
b101110110000 A
b101110110000 N
b1100 7
b111111111111111100010001100011111101101010111100 4
b1100101111001111110000100111111010 $
b1100101111001111110000100111111010 5
b11111111111111011101010000000110 <
b11111111111111010000011111111100 =
b1100 6
b1100 >
b1101 F
b111111110011110100101101001100 C
b10001101101011101110001000101001 #
b10001101101011101110001000101001 D
b1101011010110010 K
b11101011101001 L
b1101 E
b1101 M
1+
#1083342
0+
#1125009
b10001011011111 B
b1001000101 A
b1001000101 N
b10110100011110011 3
b101110110000 2
b101110110000 ?
b1110 F
b111101110100110001000001011000 C
b10001100000101101111001000110110 #
b10001100000101101111001000110110 D
b1101000000000100 K
b1101011010110010 L
b1110 E
b1110 M
b1101 7
b111111111111111111001100010100100110101100000000 4
b1101011001000110010011001111011011 $
b1101011001000110010011001111011011 5
b11111111111111111000011110000000 <
b11111111111111011101010000000110 =
b1101 6
b1101 >
1+
#1166676
0+
#1208343
b101110010111110110 3
b1001000101 2
b1001000101 ?
b11111111111111111000011110001011 B
b10111000011011 A
b10111000011011 N
b1110 7
b10011010110011000100011010111110 4
b1101100000101111100011101011001110 $
b1101100000101111100011101011001110 5
b10110100011110011 <
b11111111111111111000011110000000 =
b1110 6
b1110 >
b1111 F
b1010010111010011001100101010 C
b1010000111011111001011000001011 #
b1010000111011111001011000001011 D
b10001011011111 K
b1101000000000100 L
b1111 E
b1111 M
1+
#1250010
0+
#1291677
b11111111111111110111111000001100 B
b11000000100000 A
b11000000100000 N
b111011110111110100 3
b10111000011011 2
b10111000011011 ?
b10000 F
b111111111111111111011100001100101110100111110010 C
b110001111100111101011110110001 #
b110001111100111101011110110001 D
b11111111111111111000011110001011 K
b10001011011111 L
b10000 E
b10000 M
b1111 7
b100111110001100110011001000011100 4
b1111001100010000011000110001111011 $
b1111001100010000011000110001111011 5
b101110010111110110 <
b10110100011110011 =
b1111 6
b1111 >
1+
#1333344
0+
#1375011
b111011010101111101 3
b11000000100000 2
b11000000100000 ?
b11111111111111111011101001111011 B
b1101110010000101 A
b1101110010000101 N
b10000 7
b110011010110101001100011010001000 4
b1111110011010001001011100000101101 $
b1111110011010001001011100000101101 5
b111011110111110100 <
b101110010111110110 =
b10000 6
b10000 >
b10001 F
b111111111111111111011001011000000110010100001000 C
b101010111001000111000011101000 #
b101010111001000111000011101000 D
b11111111111111110111111000001100 K
b11111111111111111000011110001011 L
b10001 E
b10001 M
1+
#1416678
0+
#1458345
b11111111111111111011011100110011 B
b1000011111100101 A
b1000011111100101 N
b100111101101011110 3
b1101110010000101 2
b1101110010000101 ?
b10010 F
b111111111111111111101011010101101000101010010010 C
b10000000101000001100001011011 #
b10000000101000001100001011011 D
b11111111111111111011101001111011 K
b11111111111111110111111000001100 L
b10010 E
b10010 M
b10001 7
b110010111001100110110110110100010 4
b10000011111111110110001111001000001 $
b10000011111111110110001111001000001 5
b111011010101111101 <
b111011110111110100 =
b10001 6
b10001 >
1+
#1500012
0+
#1541679
b1010001011001 3
b1000011111100101 2
b1000011111100101 ?
b11111111111111111000100110011111 B
b1001101010100111 A
b1001101010100111 N
b10010 7
b100010000011111000101111000101100 4
b10111010011111001111011001100010101 $
b10111010011111001111011001100010101 5
b100111101101011110 <
b111011010101111101 =
b10010 6
b10010 >
b10011 F
b111111111111111111101010010111001110001001100010 C
b100011011010111111101100010110 #
b100011011010111111101100010110 D
b11111111111111111011011100110011 K
b11111111111111111011101001111011 L
b10011 E
b10011 M
1+
#1583346
0+
#1625013
b11111111111111111011110110100101 B
b110010100 A
b110010100 N
b11111111111111010100001000110000 3
b1001101010100111 2
b1001101010100111 ?
b10100 F
b111111111111111111011100110100010000011110101010 C
b100011011101100010011000111001 #
b100011011101100010011000111001 D
b11111111111111111000100110011111 K
b11111111111111111011011100110011 L
b10100 E
b10100 M
b10011 7
b1000101110011111001100111010 4
b11111100101010010111110100001011111 $
b11111100101010010111110100001011111 5
b1010001011001 <
b100111101101011110 =
b10011 6
b10011 >
1+
#1666680
0+
#1708347
b11111111111110110011100101001101 3
b110010100 2
b110010100 ?
b110111000011011 B
b100011010011101 A
b100011010011101 N
b10100 7
b111111111111111011010011000001001010100111100000 4
b11111011101101001010110011011000010 $
b11111011101101001010110011011000010 5
b11111111111111010100001000110000 <
b1010001011001 =
b10100 6
b10100 >
b10101 F
b111111111111111111101100010001110100100000101110 C
b1100010011111000001000100010001 #
b1100010011111000001000100010001 D
b11111111111111111011110110100101 K
b11111111111111111000100110011111 L
b10101 E
b10101 M
1+
#1750014
0+
#1791681
b1111010010100001 B
b10111101100001 A
b10111101100001 N
b11111111111110101101001011110000 3
b100011010011101 2
b100011010011101 ?
b10110 F
b100000101110010111101001010010 C
b10011100000010010000111100101010 #
b10011100000010010000111100101010 D
b110111000011011 K
b11111111111111111011110110100101 L
b10110 E
b10110 M
b10101 7
b111111111111110111110011101000001111111111000010 4
b11100110001101111100001100101100110 $
b11100110001101111100001100101100110 5
b11111111111110110011100101001101 <
b11111111111111010100001000110000 =
b10101 6
b10101 >
1+
#1833348
0+
#1875015
b11111111111111000001010011111110 3
b10111101100001 2
b10111101100001 ?
b1011011100011000 B
b1001100000 A
b1001100000 N
b10110 7
b111111111111110111000111101110101010000101100000 4
b11101011010011001100110001111100110 $
b11101011010011001100110001111100110 5
b11111111111110101101001011110000 <
b11111111111110110011100101001101 =
b10110 6
b10110 >
b10111 F
b1001000101101001101000111010110 C
b10011100101101100101001110110011 #
b10011100101101100101001110110011 D
b1111010010100001 K
b110111000011011 L
b10111 E
b10111 M
1+
#1916682
0+
#1958349
b11111111111111111111100111111001 B
b1010011101111 A
b1010011101111 N
b11111111111111100111011011010010 3
b1001100000 2
b1001100000 ?
b11000 F
b110110011010101101110000010000 C
b10001000001101111001111011000011 #
b10001000001101111001111011000011 D
b1011011100011000 K
b1111010010100001 L
b11000 E
b11000 M
b10111 7
b111111111111111001010001110110001011011001101100 4
b11101100011000010001000010000111011 $
b11101100011000010001000010000111011 5
b11111111111111000001010011111110 <
b11111111111110101101001011110000 =
b10111 6
b10111 >
1+
#2000016
0+
#2041683
b10101110101110101 3
b1010011101111 2
b1010011101111 ?
b11111111111111111000101101111101 B
b100100111000000 A
b100100111000000 N
b11000 7
b111111111111111101010111011000010010101110110100 4
b11111010001100111001101101111001000 $
b11111010001100111001101101111001000 5
b11111111111111100111011011010010 <
b11111111111111000001010011111110 =
b11000 6
b11000 >
b11001 F
b111111111111111111111110001101010110011101100110 C
b110001111010000110111111110011 #
b110001111010000110111111110011 D
b11111111111111111111100111111001 K
b1011011100011000 L
b11001 E
b11001 M
1+
#2083350
0+
#2125017
b11111111111111111011011101001010 B
b11101111000111 A
b11101111000111 N
b1000010101001101000 3
b100100111000000 2
b100100111000000 ?
b11010 F
b111111111111111111011101010111110001100010111110 C
b100010010101100101111010110010 #
b100010010101100101111010110010 D
b11111111111111111000101101111101 K
b11111111111111111111100111111001 L
b11010 E
b11010 M
b11001 7
b10010101110111101000111101010010 4
b100101110110000101111111010011100011 $
b100101110110000101111111010011100011 5
b10101110101110101 <
b11111111111111100111011011010010 =
b11001 6
b11001 >
1+
#2166684
0+
#2208351
b1100000001110110000 3
b11101111000111 2
b11101111000111 ?
b11111111111111111111010111010111 B
b1101011111000110 A
b1101011111000110 N
b11010 7
b111001001010101111011111000010000 4
b101010001100000000000100001110001101 $
b101010001100000000000100001110001101 5
b1000010101001101000 <
b10101110101110101 =
b11010 6
b11010 >
b11011 F
b111111111111111111101010011000111011100001011100 C
b10001100111111101100010100110 #
b10001100111111101100010100110 D
b11111111111111111011011101001010 K
b11111111111111111000101101111101 L
b11011 E
b11011 M
1+
#2250018
0+
#2291685
b11111111111111111100001001011110 B
b1000010110111101 A
b1000010110111101 N
b1011111111010100001 3
b1101011111000110 2
b1101011111000110 ?
b11100 F
b111111111111111111111100111110101111010001111010 C
b1100010101010110000101010101 #
b1100010101010110000101010101 D
b11111111111111111111010111010111 K
b11111111111111111011011101001010 L
b11100 E
b11100 M
b11011 7
b1010010100010100001101100011100000 4
b101001000010011011001001000010100111 $
b101001000010011011001001000010100111 5
b1100000001110110000 <
b1000010101001101000 =
b11011 6
b11011 >
1+
#2333352
0+
#2375019
b111100101010100010 3
b1000010110111101 2
b1000010110111101 ?
b11111111111111110110001011011111 B
b1010000111111100 A
b1010000111111100 N
b11100 7
b1010010010001001010111100000001010 4
b101101010010001101000001110110010110 $
b101101010010001101000001110110010110 5
b1011111111010100001 <
b1100000001110110000 =
b11100 6
b11100 >
b11101 F
b111111111111111111101101101011101001110000010100 C
b1000010010011101111110110101111 #
b1000010010011101111110110101111 D
b11111111111111111100001001011110 K
b11111111111111111111010111010111 L
b11101 E
b11101 M
1+
#2416686
0+
#2458353
b11111111111111111000010011010001 B
b111111101 A
b111111101 N
b10010001101110 3
b1010000111111100 2
b1010000111111100 ?
b11110 F
b111111111111111111010001010011001011001100101010 C
b1000001110101001100110110001011 #
b1000001110101001100110110001011 D
b11111111111111110110001011011111 K
b11111111111111111100001001011110 L
b11110 E
b11110 M
b11101 7
b110100000010001001101110111010100 4
b110101111000011011001111101010100100 $
b110101111000011011001111101010100100 5
b111100101010100010 <
b1011111111010100001 =
b11101 6
b11101 >
1+
#2500020
0+
#2541687
b11111111111111000111010111011001 3
b111111101 2
b111111101 ?
b11110010100010 B
b11000111110100 A
b11000111110100 N
b11110 7
b1111100111111001010011001100 4
b110101101001110110111100100011011100 $
b110101101001110110111100100011011100 5
b10010001101110 <
b111100101010100010 =
b11110 6
b11110 >
b11111 F
b111111111111111111011011011000110111010111110110 C
b1101100010100011111011011001100 #
b1101100010100011111011011001100 D
b11111111111111111000010011010001 K
b11111111111111110110001011011111 L
b11111 E
b11111 M
1+
#2583354
0+
