verilog/decoder/sinwave.v
module sinwave (
    input  wire [6:0] addr,
    output reg signed [15:0] sample
);
    always @(*) begin
        case (addr)
7'd0: sample = 16'sd0;
7'd1: sample = 16'sd31415;
7'd2: sample = 16'sd17861;
7'd3: sample = -16'sd21261;
7'd4: sample = -16'sd29948;
7'd5: sample = 16'sd4234;
7'd6: sample = 16'sd32355;
7'd7: sample = 16'sd14161;
7'd8: sample = -16'sd24305;
7'd9: sample = -16'sd27979;
7'd10: sample = 16'sd8398;
7'd11: sample = 16'sd32753;
7'd12: sample = 16'sd10223;
7'd13: sample = -16'sd26941;
7'd14: sample = -16'sd25540;
7'd15: sample = 16'sd12420;
7'd16: sample = 16'sd32602;
7'd17: sample = 16'sd6115;
7'd18: sample = -16'sd29125;
7'd19: sample = -16'sd22673;
7'd20: sample = 16'sd16235;
7'd21: sample = 16'sd31903;
7'd22: sample = 16'sd1903;
7'd23: sample = -16'sd30821;
7'd24: sample = -16'sd19426;
7'd25: sample = 16'sd19777;
7'd26: sample = 16'sd30670;
7'd27: sample = -16'sd2340;
7'd28: sample = -16'sd32000;
7'd29: sample = -16'sd15853;
7'd30: sample = 16'sd22987;
7'd31: sample = 16'sd28922;
7'd32: sample = -16'sd6544;
7'd33: sample = -16'sd32643;
7'd34: sample = -16'sd12014;
7'd35: sample = 16'sd25812;
7'd36: sample = 16'sd26689;
7'd37: sample = -16'sd10638;
7'd38: sample = -16'sd32738;
7'd39: sample = -16'sd7974;
7'd40: sample = 16'sd28204;
7'd41: sample = 16'sd24009;
7'd42: sample = -16'sd14554;
7'd43: sample = -16'sd32283;
7'd44: sample = -16'sd3800;
7'd45: sample = 16'sd30123;
7'd46: sample = 16'sd20926;
7'd47: sample = -16'sd18226;
7'd48: sample = -16'sd31288;
7'd49: sample = 16'sd437;
7'd50: sample = 16'sd31537;
7'd51: sample = 16'sd17492;
7'd52: sample = -16'sd21592;
7'd53: sample = -16'sd29768;
7'd54: sample = 16'sd4668;
7'd55: sample = 16'sd32422;
7'd56: sample = 16'sd13765;
7'd57: sample = -16'sd24596;
7'd58: sample = -16'sd27749;
7'd59: sample = 16'sd8820;
7'd60: sample = 16'sd32763;
7'd61: sample = 16'sd9807;
7'd62: sample = -16'sd27187;
7'd63: sample = -16'sd25264;
7'd64: sample = 16'sd12824;
7'd65: sample = 16'sd32555;
7'd66: sample = 16'sd5684;
7'd67: sample = -16'sd29323;
7'd68: sample = -16'sd22355;
7'd69: sample = 16'sd16613;
7'd70: sample = 16'sd31801;
7'd71: sample = 16'sd1466;
7'd72: sample = -16'sd30967;
7'd73: sample = -16'sd19072;
7'd74: sample = 16'sd20124;
7'd75: sample = 16'sd30513;
7'd76: sample = -16'sd2776;
7'd77: sample = -16'sd32091;
7'd78: sample = -16'sd15469;
7'd79: sample = 16'sd23297;
7'd80: sample = 16'sd28714;
7'd81: sample = -16'sd6972;
7'd82: sample = -16'sd32678;
7'd83: sample = -16'sd11606;
7'd84: sample = 16'sd26079;
7'd85: sample = 16'sd26433;
7'd86: sample = -16'sd11051;
7'd87: sample = -16'sd32716;
7'd88: sample = -16'sd7549;
7'd89: sample = 16'sd28424;
7'd90: sample = 16'sd23709;
7'd91: sample = -16'sd14945;
7'd92: sample = -16'sd32206;
7'd93: sample = -16'sd3365;
7'd94: sample = 16'sd30292;
7'd95: sample = 16'sd20588;
7'd96: sample = -16'sd18588;
7'd97: sample = -16'sd31155;
7'd98: sample = 16'sd875;
7'd99: sample = 16'sd31653;
7'd100: sample = 16'sd17121;
7'd101: sample = -16'sd21919;
7'd102: sample = -16'sd29582;
7'd103: sample = 16'sd5100;
7'd104: sample = 16'sd32482;
7'd105: sample = 16'sd13367;
7'd106: sample = -16'sd24883;
7'd107: sample = -16'sd27513;
7'd108: sample = 16'sd9241;
7'd109: sample = 16'sd32767;
7'd110: sample = 16'sd9389;
7'd111: sample = -16'sd27429;
7'd112: sample = -16'sd24983;
7'd113: sample = 16'sd13226;
7'd114: sample = 16'sd32502;
7'd115: sample = 16'sd5253;
7'd116: sample = -16'sd29516;
7'd117: sample = -16'sd22034;
7'd118: sample = 16'sd16989;
7'd119: sample = 16'sd31692;
7'd120: sample = 16'sd1029;
7'd121: sample = -16'sd31107;
7'd122: sample = -16'sd18715;
7'd123: sample = 16'sd20467;
7'd124: sample = 16'sd30351;
7'd125: sample = -16'sd3212;
7'd126: sample = -16'sd32177;
7'd127: sample = -16'sd15082;

            default: sample = 16'sd0;
        endcase
    end
endmodule

verilog/decoder/goertzel.v
// module goertzel
// (

//     input wire clk,reset,
// output reg signed [15:0] maxcoeff,
// output wire signed [15:0] COEFF_tb,
//     output reg signed [63:0] power_tb,
//     output reg signed [63:0] max_power,
//     output wire signed [63:0] power
// );

// reg [6:0] addr = 7'd0;
// wire signed [15:0] sample;

// localparam integer Fs = 8000;
// localparam integer N  = 128;
// localparam signed [15:0] COEFFF =
//     (F == 697)  ? 16'sd28106 :
//     (F == 770)  ? 16'sd27018 :
//     (F == 852)  ? 16'sd25330 :
//     (F == 941)  ? 16'sd24126 :
//     (F == 1209) ? 16'sd19478 :
//     (F == 1336) ? 16'sd16846 :
//     (F == 1477) ? 16'sd12490 :
//     (F == 1633) ? 16'sd9220  :
//                   16'sd28106;

// reg signed [15:0] COEFF [0:7];

// // Fixed: Correctly initialize the array inside an initial block

// always @(*) begin
  
//     if(reset) begin
//         max_power=0;
//         maxcoeff=0;
//         count = 0;
//         s1 = 0;
//         s2 = 0;
//         addr = 0;

//     end

// end 

// initial begin
//     COEFF[0] = 16'sd28106; // 697 Hz
//     COEFF[1] = 16'sd27018; // 770 Hz
//     COEFF[2] = 16'sd25330; // 852 Hz
//     COEFF[3] = 16'sd24126; // 941 Hz
//     COEFF[4] = 16'sd19478; // 1209 Hz
//     COEFF[5] = 16'sd16846; // 1336 Hz
//     COEFF[6] = 16'sd12490; // 1477 Hz
//     COEFF[7] = 16'sd9220;  // 1633 Hz
// end
// // Add this inside module goertzel

// reg [2:0] i = 3'd0;
// reg signed [31:0] s1 = 0;
// reg signed [31:0] s2 = 0;

// wire signed [31:0] s_next;

// reg [6:0] count = 0;

// assign COEFF_tb=COEFF[i];
// assign s_next =
//       {{16{sample[15]}}, sample}
//     + ((COEFF[i] * s1) >>> 14)
//     - s2;

// assign power =
//               (s_next * s_next)
//             + (s1 * s1)
//             - (((COEFF[i] * s_next * s1) >>> 14));


// always @(posedge clk) begin
  
//     if(count == 7'd127) power_tb<=power;

// end


// always @(*) begin
  
//         if(power>max_power) begin
//           max_power=power;
//           maxcoeff=COEFF[i];

//         end
//         else begin
          
//           max_power=max_power;
//           maxcoeff=maxcoeff;
          
//         end

// end




// always @(posedge clk) begin

//     addr <= addr + 1'b1;

//     if(count == 7'd127) begin



//         count <= 0;
//         s1 <= 0;
//         s2 <= 0;
//         addr <= 0;

//        if (i == 7) begin
//             i <= 0;
//         end else begin
//             i <= i + 1'b1;
//         end
//     end
//     else begin

//         s2 <= s1;
//         s1 <= s_next;

//         count <= count + 1'b1;

//     end
// end

// sinwave sw(
//     .addr(addr),
//     .sample(sample)
// );

// endmodule
module goertzel (
    input wire clk,
    input wire reset,
    output reg signed [15:0] maxcoeff,
    output wire signed [15:0] COEFF_tb,
    output reg signed [63:0] power_tb,
    output reg signed [63:0] max_power,
    output wire signed [63:0] power
);

    reg [6:0] addr = 7'd0;
    wire signed [15:0] sample;
    reg [2:0] i = 3'd0;
    reg signed [31:0] s1 = 32'sd0;
    reg signed [31:0] s2 = 32'sd0;
    reg [6:0] count = 7'd0;

    // DTMF Coefficients Array
    reg signed [15:0] COEFF [0:7];
    initial begin
        COEFF[0] = 16'sd28106; // 697 Hz
        COEFF[1] = 16'sd27018; // 770 Hz
        COEFF[2] = 16'sd25330; // 852 Hz
        COEFF[3] = 16'sd24126; // 941 Hz
        COEFF[4] = 16'sd19478; // 1209 Hz
        COEFF[5] = 16'sd16846; // 1336 Hz
        COEFF[6] = 16'sd12490; // 1477 Hz
        COEFF[7] = 16'sd9220;  // 1633 Hz
    end

    assign COEFF_tb = COEFF[i];

    // Goertzel state update equation
    wire signed [31:0] s_next;
    assign s_next = {{16{sample[15]}}, sample} + ((COEFF[i] * s1) >>> 14) - s2;

    // Scale intermediate variables down by 4 bits to prevent overflow during multiplication
    wire signed [63:0] s_next_scaled = s_next >>> 4;
    wire signed [63:0] s1_scaled     = s1 >>> 4;

    // Power calculation
    assign power = (s_next_scaled * s_next_scaled) 
                 + (s1_scaled * s1_scaled) 
                 - (((COEFF[i] * s_next_scaled * s1_scaled) >>> 14));

    // EVERYTHING IS CONTROLLED HERE (NO ALWAYS @(*) FOR MAX TRACKING)
    always @(posedge clk) begin
        if (reset) begin
            addr      <= 7'd0;
            count     <= 7'd0;
            i         <= 3'd0;
            s1        <= 32'sd0;
            s2        <= 32'sd0;
            max_power <= 64'sd0;
            maxcoeff  <= 16'sd0;
            power_tb  <= 64'sd0;
        end else begin
            addr <= addr + 1'b1;

            if (count == 7'd127) begin
                power_tb <= power;
                
                // Track peak strictly on the clock edge
                if (power > max_power) begin
                    max_power <= power;
                    maxcoeff  <= COEFF[i];
                end

                // Reset step accumulation
                count <= 7'd0;
                s1    <= 32'sd0;
                s2    <= 32'sd0;
                addr  <= 7'd0;

                // Move to the next coefficient block
                if (i == 3'd7) begin
                    i <= 3'd0;
                end else begin
                    i <= i + 1'b1;
                end
            end else begin
                s2    <= s1;
                s1    <= s_next;
                count <= count + 1'b1;
            end
        end
    end

    // Rom Instantiation
    sinwave sw (
        .addr(addr),
        .sample(sample)
    );

endmodule

verilog/decoder/testbench.v
// `timescale 1ps/1ps

// module tb_goertzel;

// reg clk;
// reg reset;
// initial begin
//     clk = 0;
//     reset=1;
//     #100
//     reset=0;
//     forever #41667 clk = ~clk;
// end

// wire signed [15:0] maxcoeff;
//     wire signed [63:0] power ;
//     wire signed [63:0] power_tb ;
//     wire signed [63:0] max_power ;
//     wire signed [15:0] COEFF_tb;
// goertzel dut(
// .clk(clk),
//     // .led_amber_n(),
//     // .led_blue_n()
// .reset(reset),
// .maxcoeff(maxcoeff),
// .power(power),
// .power_tb(power_tb),
// .COEFF_tb(COEFF_tb),
// .max_power(max_power)

// );

// integer F;
// initial begin
//     $dumpfile("wave.vcd");
//     $dumpvars(0, tb_goertzel);
// end
// initial begin
//    #90000000;  // 1 us with 1ps timescale
// case(maxcoeff) 
//     16'sd28106 : F = 697;
//     16'sd27018 : F = 770; 
//     16'sd25330 : F = 852;
//     16'sd24126 : F = 941; 
//     16'sd19478 : F = 1209; 
//     16'sd16846 : F = 1336; 
//     16'sd12490 : F = 1477; 
//     16'sd9220  : F = 1633;
//     default    : F = 0; // Highly recommended to avoid uninitialized 'x' values
// endcase
//     $display("final value is %0d %0d",F,maxcoeff);
//     $finish;
    
// end


// initial begin
//     $monitor("Time=%0t power=%0d max_power=%0d coeff=%0d max_coeff=%0d", $time, power_tb,max_power,COEFF_tb, maxcoeff);
// end
// endmodule
`timescale 1ns/1ps

module tb_goertzel;

    reg clk;
    reg reset;
    
    wire signed [15:0] maxcoeff;
    wire signed [63:0] power;
    wire signed [63:0] power_tb;
    wire signed [63:0] max_power;
    wire signed [15:0] COEFF_tb;
    integer F;

    // Instantiate Device Under Test
    goertzel dut (
        .clk(clk),
        .reset(reset),
        .maxcoeff(maxcoeff),
        .power(power),
        .power_tb(power_tb),
        .COEFF_tb(COEFF_tb),
        .max_power(max_power)
    );

    // 12 MHz Clock Generator (Period = 83.333 ns -> Half-Period = 41.667 ns)
    always #41.667 clk = ~clk;

    initial begin
        $dumpfile("wave.vcd");
        $dumpvars(0, tb_goertzel);
        
        // Initialize signals
        clk = 0;
        reset = 1;
        
        // Hold reset for 3 full clock cycles
        #250; 
        reset = 0;
        
        // Print progress monitor directly to the terminal
        $monitor("Time=%0t ns | Bin Index=%0d | Coeff=%0d | Power=%0d | Peak Power Found=%0d", 
                 $time, dut.i, COEFF_tb, power_tb, max_power);
        
        // --- DYNAMIC TERMINATION ---
        // Instead of hardcoding delays, we wait until the design finishes the 
        // 8th frequency bin (index i = 7) and the 128th sample (count = 127).
        @(posedge clk);
        while (dut.i !== 3'd7 || dut.count !== 7'd127) begin
            @(posedge clk);
        end
        
        // Wait 1 final clock cycle to allow the final comparison logic 
        // to update the register outputs (maxcoeff, max_power)
        @(posedge clk);

        // Map the highest recorded coefficient to its corresponding frequency
        case(maxcoeff) 
            16'sd28106 : F = 697;
            16'sd27018 : F = 770; 
            16'sd25330 : F = 852;
            16'sd24126 : F = 941; 
            16'sd19478 : F = 1209;
            16'sd16846 : F = 1336; 
            16'sd12490 : F = 1477; 
            16'sd9220  : F = 1633;
            default    : F = 0;
        endcase

        $display("\n=================================");
        $display("       DETECTION COMPLETE        ");
        $display("=================================");
        $display("Detected Frequency : %0d Hz", F);
        $display("Winning Coefficient: %0d", maxcoeff);
        $display("Peak Calculated Power: %0d", max_power);
        $display("=================================\n");
        
        $finish;
    end

endmodule

verilog/decoder/wave.vcd
$date
	Fri Jun 19 22:26:57 2026
$end
$version
	Icarus Verilog
$end
$timescale
	1ps
$end
$scope module tb_goertzel $end
$var wire 64 ! power_tb [63:0] $end
$var wire 64 " power [63:0] $end
$var wire 16 # maxcoeff [15:0] $end
$var wire 64 $ max_power [63:0] $end
$var wire 16 % COEFF_tb [15:0] $end
$var reg 1 & clk $end
$var reg 1 ' reset $end
$var integer 32 ( F [31:0] $end
$scope module dut $end
$var wire 16 ) COEFF_tb [15:0] $end
$var wire 1 & clk $end
$var wire 1 ' reset $end
$var wire 16 * sample [15:0] $end
$var wire 64 + s_next_scaled [63:0] $end
$var wire 32 , s_next [31:0] $end
$var wire 64 - s1_scaled [63:0] $end
$var wire 64 . power [63:0] $end
$var reg 7 / addr [6:0] $end
$var reg 7 0 count [6:0] $end
$var reg 3 1 i [2:0] $end
$var reg 64 2 max_power [63:0] $end
$var reg 16 3 maxcoeff [15:0] $end
$var reg 64 4 power_tb [63:0] $end
$var reg 32 5 s1 [31:0] $end
$var reg 32 6 s2 [31:0] $end
$scope module sw $end
$var wire 7 7 addr [6:0] $end
$var reg 16 8 sample [15:0] $end
$upscope $end
$upscope $end
$upscope $end
$enddefinitions $end
#0
$dumpvars
b0 8
b0 7
b0 6
b0 5
bx 4
bx 3
bx 2
b0 1
b0 0
b0 /
b0 .
b0 -
b0 ,
b0 +
b0 *
b110110111001010 )
bx (
1'
0&
b110110111001010 %
bx $
bx #
b0 "
bx !
$end
#41667
b0 !
b0 4
b0 #
b0 3
b0 $
b0 2
1&
#83334
0&
#125001
1&
#166668
0&
#208335
1&
#250000
0'
#250002
0&
#291669
b1110101100110000111001 "
b1110101100110000111001 .
b11110101011 +
b111101010110111 ,
b111101010110111 *
b111101010110111 8
b1 0
b1 /
b1 7
1&
#333336
0&
#375003
b1000110000100 +
b100001110011000110001001 "
b100001110011000110001001 .
b11110101011 -
b10001100001000111 ,
b100010111000101 *
b100010111000101 8
b10 0
b111101010110111 5
b10 /
b10 7
1&
#416670
0&
#458337
b1000110000100 -
b10101011100010100101001 "
b10101011100010100101001 .
b1000100110000 +
b1010110011110011 *
b1010110011110011 8
b11 0
b10001100001000111 5
b10001001100001001 ,
b111101010110111 6
b11 /
b11 7
1&
#500004
0&
#541671
b1000100110000 -
b101100111100110111100011 "
b101100111100110111100011 .
b10010101000 +
b1000101100000100 *
b1000101100000100 8
b100 0
b10001001100001001 5
b100101010001100 ,
b10001100001000111 6
b100 /
b100 7
1&
#583338
0&
#625005
b10010101000 -
b100110011000101100110001 "
b100110011000101100110001 .
b1111111111111111111111111111111111111111111111111111011111010110 +
b1000010001010 *
b1000010001010 8
b101 0
b100101010001100 5
b11111111111111110111110101100010 ,
b10001001100001001 6
b101 /
b101 7
1&
#666672
0&
#708339
b1111111111111111111111111111111111111111111111111111011111010110 -
b1110001111100001101000011100 "
b1110001111100001101000011100 .
b11010100111100 +
b111111001100011 *
b111111001100011 8
b110 0
b11111111111111110111110101100010 5
b110101001111000101 ,
b100101010001100 6
b110 /
b110 7
1&
#750006
0&
#791673
b11010100111100 -
b11000110100010100010100001 "
b11000110100010100010100001 .
b10011011110001 +
b11011101010001 *
b11011101010001 8
b111 0
b110101001111000101 5
b100110111100011010 ,
b11111111111111110111110101100010 6
b111 /
b111 7
1&
#833340
0&
#875007
b10011011110001 -
b100001000010100111000110001010 "
b100001000010100111000110001010 .
b1111111111111111111111111111111111111111111111111100011110100011 +
b1010000100001111 *
b1010000100001111 8
b1000 0
b100110111100011010 5
b11111111111111000111101000110000 ,
b110101001111000101 6
b1000 /
b1000 7
1&
#916674
0&
#958341
b1111111111111111111111111111111111111111111111111100011110100011 -
b111110000110111011100100011 "
b111110000110111011100100011 .
b1111111111111111111111111111111111111111111111111111000110001001 +
b1001001010110101 *
b1001001010110101 8
b1001 0
b11111111111111000111101000110000 5
b11111111111111110001100010010110 ,
b100110111100011010 6
b1001 /
b1001 7
1&
#1000008
0&
#1041675
b1111111111111111111111111111111111111111111111111111000110001001 -
b101111011111010010100011110100 "
b101111011111010010100011110100 .
b110000110011010 +
b10000011001110 *
b10000011001110 8
b1010 0
b11111111111111110001100010010110 5
b1100001100110100011 ,
b11111111111111000111101000110000 6
b1010 /
b1010 7
1&
#1083342
0&
#1125009
b110000110011010 -
b1011101100100001101011101110 "
b1011101100100001101011101110 .
b11110111100100 +
b111111111110001 *
b111111111110001 8
b1011 0
b1100001100110100011 5
b111101111001000101 ,
b11111111111111110001100010010110 6
b1011 /
b1011 7
1&
#1166676
0&
#1208343
b11110111100100 -
b101111110111010011101100001010 "
b101111110111010011101100001010 .
b1111111111111111111111111111111111111111111111111100101100010000 +
b10011111101111 *
b10011111101111 8
b1100 0
b111101111001000101 5
b11111111111111001011000100001111 ,
b1100001100110100011 6
b1100 /
b1100 7
1&
#1250010
0&
#1291677
b1111111111111111111111111111111111111111111111111100101100010000 -
b11101011000100110000110011 "
b11101011000100110000110011 .
b1111111111111111111111111111111111111111111111111110000010111001 +
b1001011011000011 *
b1001011011000011 8
b1101 0
b11111111111111001011000100001111 5
b11111111111111100000101110011010 ,
b111101111001000101 6
b1101 /
b1101 7
1&
#1333344
0&
#1375011
b1111111111111111111111111111111111111111111111111110000010111001 -
b11100011111010111010110100111 "
b11100011111010111010110100111 .
b11100100001100 +
b1001110000111100 *
b1001110000111100 8
b1110 0
b11111111111111100000101110011010 5
b111001000011000011 ,
b11111111111111001011000100001111 6
b1110 /
b1110 7
1&
#1416678
0&
#1458345
b11100100001100 -
b100110011100011011001010001 "
b100110011100011011001010001 .
b100010000101011 +
b11000010000100 *
b11000010000100 8
b1111 0
b111001000011000011 5
b1000100001010110111 ,
b11111111111111100000101110011010 6
b1111 /
b1111 7
1&
#1500012
0&
#1541679
b100010000101011 -
b10000011100110100111011111101 "
b10000011100110100111011111101 .
b1111011010 +
b111111101011010 *
b111111101011010 8
b10000 0
b1000100001010110111 5
b11110110101001 ,
b111001000011000011 6
b10000 /
b10000 7
1&
#1583346
0&
#1625013
b1111011010 -
b1111101100111010110101011100 "
b1111101100111010110101011100 .
b1111111111111111111111111111111111111111111111111100001111101111 +
b1011111100011 *
b1011111100011 8
b10001 0
b11110110101001 5
b11111111111111000011111011110010 ,
b1000100001010110111 6
b10001 /
b10001 7
1&
#1666680
0&
#1708347
b1111111111111111111111111111111111111111111111111100001111101111 -
b10100011111011000011010011000 "
b10100011111011000011010011000 .
b110111111110 +
b1000111000111011 *
b1000111000111011 8
b10010 0
b11111111111111000011111011110010 5
b1101111111101100 ,
b11110110101001 6
b10010 /
b10010 7
1&
#1750014
0&
#1791681
b110111111110 -
b10001011111100111100111101010 "
b10001011111100111100111101010 .
b100111010001001 +
b1010011101101111 *
b1010011101101111 8
b10011 0
b1101111111101100 5
b1001110100010011101 ,
b11111111111111000011111011110010 6
b10011 /
b10011 7
1&
#1833348
0&
#1875015
b100111010001001 -
b11001110111111110100100100001 "
b11001110111111110100100100001 .
b1111111111111111111111111111111111111111111111111111110010110010 +
b11111101101011 *
b11111101101011 8
b10100 0
b1001110100010011101 5
b11111111111111111100101100101000 ,
b1101111111101100 6
b10100 /
b10100 7
1&
#1916682
0&
#1958349
b1111111111111111111111111111111111111111111111111111110010110010 -
b10111101011101010011101 "
b10111101011101010011101 .
b1111111111111111111111111111111111111111111111111111001110010101 +
b111110010011111 *
b111110010011111 8
b10101 0
b11111111111111111100101100101000 5
b11111111111111110011100101011011 ,
b1001110100010011101 6
b10101 /
b10101 7
1&
#2000016
0&
#2041683
b1111111111111111111111111111111111111111111111111111001110010101 -
b1100111001110111001011111100 "
b1100111001110111001011111100 .
b10111001111000 +
b11101101111 *
b11101101111 8
b10110 0
b11111111111111110011100101011011 5
b101110011110000011 ,
b11111111111111111100101100101000 6
b10110 /
b10110 7
1&
#2083350
0&
#2125017
b10111001111000 -
b11101011010101110101101111 "
b11101011010101110101101111 .
b1010010011011 +
b1000011110011011 *
b1000011110011011 8
b10111 0
b101110011110000011 5
b10100100110110101 ,
b11111111111111110011100101011011 6
b10111 /
b10111 7
1&
#2166684
0&
#2208351
b1010010011011 -
b100110101001111010111001010 "
b100110101001111010111001010 .
b1111111111111111111111111111111111111111111111111111000000100011 +
b1011010000011110 *
b1011010000011110 8
b11000 0
b10100100110110101 5
b11111111111111110000001000110011 ,
b101110011110000011 6
b11000 /
b11000 7
1&
#2250018
0&
#2291685
b1111111111111111111111111111111111111111111111111111000000100011 -
b100111100001010011011011111 "
b100111100001010011011011111 .
b1010100000010 +
b100110101000001 *
b100110101000001 8
b11001 0
b11111111111111110000001000110011 5
b10101000000101001 ,
b10100100110110101 6
b11001 /
b11001 7
1&
#2333352
0&
#2375019
b1010100000010 -
b111001001000100001001000101 "
b111001001000100001001000101 .
b11101101100100 +
b111011111001110 *
b111011111001110 8
b11010 0
b10101000000101001 5
b111011011001000101 ,
b11111111111111110000001000110011 6
b11010 /
b11010 7
1&
#2416686
0&
#2458353
b11101101100100 -
b1000010101000011010100011000 "
b1000010101000011010100011000 .
b1000001001101 +
b1111011011011100 *
b1111011011011100 8
b11011 0
b111011011001000101 5
b10000010011010111 ,
b10101000000101001 6
b11011 /
b11011 7
1&
#2500020
0&
#2541687
b1000001001101 -
b1011010101101001011001110111 "
b1011010101101001011001110111 .
b1111111111111111111111111111111111111111111111111101100011000011 +
b1000001100000000 *
b1000001100000000 8
b11100 0
b10000010011010111 5
b11111111111111011000110000110000 ,
b111011011001000101 6
b11100 /
b11100 7
1&
#2583354
0&
#2625021
b1111111111111111111111111111111111111111111111111101100011000011 -
b10111000101000101001100101100 "
b10111000101000101001100101100 .
b10100010000100 +
b1100001000010011 *
b1100001000010011 8
b11101 0
b11111111111111011000110000110000 5
b101000100001000000 ,
b10000010011010111 6
b11101 /
b11101 7
1&
#2666688
0&
#2708355
b10100010000100 -
b10101001010011100111110111 "
b10101001010011100111110111 .
b11001001011010 +
b101100111001011 *
b101100111001011 8
b11110 0
b101000100001000000 5
b110010010110100110 ,
b11111111111111011000110000110000 6
b11110 /
b11110 7
1&
#2750022
0&
#2791689
b11001001011010 -
b1110000111101110001011110101 "
b1110000111101110001011110101 .
b1111111111111111111111111111111111111111111111111111010011101100 +
b111000011111010 *
b111000011111010 8
b11111 0
b110010010110100110 5
b11111111111111110100111011000111 ,
b101000100001000000 6
b11111 /
b11111 7
1&
#2833356
0&
#2875023
b1111111111111111111111111111111111111111111111111111010011101100 -
b1001101110111011111011 "
b1001101110111011111011 .
b1111111111111111111111111111111111111111111111111111100100001100 +
b1110011001110000 *
b1110011001110000 8
b100000 0
b11111111111111110100111011000111 5
b11111111111111111001000011000101 ,
b110010010110100110 6
b100000 /
b100000 7
1&
#2916690
0&
#2958357
b1111111111111111111111111111111111111111111111111111100100001100 -
b1110101001110101000001110111 "
b1110101001110101000001110111 .
b11011100101110 +
b1000000001111101 *
b1000000001111101 8
b100001 0
b11111111111111111001000011000101 5
b110111001011100110 ,
b11111111111111110100111011000111 6
b100001 /
b100001 7
1&
#3000024
0&
#3041691
b11011100101110 -
b11110001001101110000100110 "
b11110001001101110000100110 .
b10001010101101 +
b1101000100010010 *
b1101000100010010 8
b100010 0
b110111001011100110 5
b100010101011011111 ,
b11111111111111111001000011000101 6
b100010 /
b100010 7
1&
#3083358
0&
#3125025
b10001010101101 -
b10101010111101111110000000 "
b10101010111101111110000000 .
b101010011100 +
b110010011010100 *
b110010011010100 8
b100011 0
b100010101011011111 5
b1010100111001001 ,
b110111001011100110 6
b100011 /
b100011 7
1&
#3166692
0&
#3208359
b101010011100 -
b1100010010001000100110001 "
b1100010010001000100110001 .
b1111111111111111111111111111111111111111111111111111011000001010 +
b110100001000001 *
b110100001000001 8
b100100 0
b1010100111001001 5
b11111111111111110110000010100100 ,
b100010101011011111 6
b100100 /
b100100 7
1&
#3250026
0&
#3291693
b1111111111111111111111111111111111111111111111111111011000001010 -
b111000100110000011000101100 "
b111000100110000011000101100 .
b10000110110100 +
b1101011001110010 *
b1101011001110010 8
b100101 0
b11111111111111110110000010100100 5
b100001101101001001 ,
b1010100111001001 6
b100101 /
b100101 7
1&
#3333360
0&
#3375027
b10000110110100 -
b100111001011001110111111110 "
b100111001011001110111111110 .
b11101111001001 +
b1000000000011110 *
b1000000000011110 8
b100110 0
b100001101101001001 5
b111011110010011000 ,
b11111111111111110110000010100100 6
b100110 /
b100110 7
1&
#3416694
0&
#3458361
b11101111001001 -
b1100110101001010011001100111 "
b1100110101001010011001100111 .
b1011101000 +
b1110000011011010 *
b1110000011011010 8
b100111 0
b111011110010011000 5
b10111010001111 ,
b100001101101001001 6
b100111 /
b100111 7
1&
#3500028
0&
#3541695
b1011101000 -
b1001111011101010111111110011 "
b1001111011101010111111110011 .
b1111111111111111111111111111111111111111111111111101000000010111 +
b110111000101100 *
b110111000101100 8
b101000 0
b10111010001111 5
b11111111111111010000000101110010 ,
b111011110010011000 6
b101000 /
b101000 7
1&
#3583362
0&
#3625029
b1111111111111111111111111111111111111111111111111101000000010111 -
b100001111010001011001101010111 "
b100001111010001011001101010111 .
b11000011000011 +
b101110111001001 *
b101110111001001 8
b101001 0
b11111111111111010000000101110010 5
b110000110000111100 ,
b10111010001111 6
b101001 /
b101001 7
1&
#3666696
0&
#3708363
b11000011000011 -
b100011000001000110001100011 "
b100011000001000110001100011 .
b100000000000010 +
b1100011100100110 *
b1100011100100110 8
b101010 0
b110000110000111100 5
b1000000000000101000 ,
b11111111111111010000000101110010 6
b101010 /
b101010 7
1&
#3750030
0&
#3791697
b100000000000010 -
b10101000111010100000111101001 "
b10101000111010100000111101001 .
b1111111111111111111111111111111111111111111111111111010100101000 +
b1000000111100101 *
b1000000111100101 8
b101011 0
b1000000000000101000 5
b11111111111111110101001010001101 ,
b110000110000111100 6
b101011 /
b101011 7
1&
#3833364
0&
#3875031
b1111111111111111111111111111111111111111111111111111010100101000 -
b100001111101000100110000 "
b100001111101000100110000 .
b1111111111111111111111111111111111111111111111111110110001110111 +
b1111000100101000 *
b1111000100101000 8
b101100 0
b11111111111111110101001010001101 5
b11111111111111101100011101110100 ,
b1000000000000101000 6
b101100 /
b101100 7
1&
#3916698
0&
#3958365
b1111111111111111111111111111111111111111111111111110110001110111 -
b10001000111110010111011010001 "
b10001000111110010111011010001 .
b11000010101111 +
b111010110101011 *
b111010110101011 8
b101101 0
b11111111111111101100011101110100 5
b110000101011110101 ,
b11111111111111110101001010001101 6
b101101 /
b101101 7
1&
#4000032
0&
#4041699
b11000010101111 -
b10011110000010111001001110 "
b10011110000010111001001110 .
b10110000101000 +
b101000110111110 *
b101000110111110 8
b101110 0
b110000101011110101 5
b101100001010001101 ,
b11111111111111101100011101110100 6
b101110 /
b101110 7
1&
#4083366
0&
#4125033
b10110000101000 -
b11010100011001111101001001011 "
b11010100011001111101001001011 .
b1111111111111111111111111111111111111111111111111101011010011110 +
b1011100011001110 *
b1011100011001110 8
b101111 0
b101100001010001101 5
b11111111111111010110100111100111 ,
b110000101011110101 6
b101111 /
b101111 7
1&
#4166700
0&
#4208367
b1111111111111111111111111111111111111111111111111101011010011110 -
b1000001111011001110111111101 "
b1000001111011001110111111101 .
b10100110110 +
b1000010111001000 *
b1000010111001000 8
b110000 0
b11111111111111010110100111100111 5
b101001101101110 ,
b101100001010001101 6
b110000 /
b110000 7
1&
#4250034
0&
#4291701
b10100110110 -
b1000010001111000001010010001 "
b1000010001111000001010010001 .
b11001001101110 +
b110110101 *
b110110101 8
b110001 0
b101001101101110 5
b110010011011101100 ,
b11111111111111010110100111100111 6
b110001 /
b110001 7
1&
#4333368
0&
#4375035
b11001001101110 -
b11111011011000110011111000 "
b11111011011000110011111000 .
b1100011111111 +
b111101100110001 *
b111101100110001 8
b110010 0
b110010011011101100 5
b11000111111111111 ,
b101001101101110 6
b110010 /
b110010 7
1&
#4416702
0&
#4458369
b1100011111111 -
b11000010000001001110111010 "
b11000010000001001110111010 .
b1111111111111111111111111111111111111111111111111111110010111001 +
b100010001010100 *
b100010001010100 8
b110011 0
b11000111111111111 5
b11111111111111111100101110010100 ,
b110010011011101100 6
b110011 /
b110011 7
1&
#4500036
0&
#4541703
b1111111111111111111111111111111111111111111111111111110010111001 -
b11101111101010101111001001 "
b11101111101010101111001001 .
b1110000011011 +
b1010101110101000 *
b1010101110101000 8
b110100 0
b11111111111111111100101110010100 5
b11100000110111011 ,
b11000111111111111 6
b110100 /
b110100 7
1&
#4583370
0&
#4625037
b1110000011011 -
b10011001011001010100100100 "
b10011001011001010100100100 .
b10110000111010 +
b1000101110111000 *
b1000101110111000 8
b110101 0
b11100000110111011 5
b101100001110100001 ,
b11111111111111111100101110010100 6
b110101 /
b110101 7
1&
#4666704
0&
