verilog/decoder/sinwave.v
module sinwave (
    input  wire [6:0] addr,
    output reg signed [15:0] sample
);
    always @(*) begin
        case (addr)
7'd0: sample = 16'sd0;
7'd1: sample = 16'sd22072;
7'd2: sample = 16'sd32626;
7'd3: sample = 16'sd26157;
7'd4: sample = 16'sd6039;
7'd5: sample = -16'sd17230;
7'd6: sample = -16'sd31509;
7'd7: sample = -16'sd29346;
7'd8: sample = -16'sd11871;
7'd9: sample = 16'sd11799;
7'd10: sample = 16'sd29312;
7'd11: sample = 16'sd31530;
7'd12: sample = 16'sd17296;
7'd13: sample = -16'sd5963;
7'd14: sample = -16'sd26110;
7'd15: sample = -16'sd32633;
7'd16: sample = -16'sd22129;
7'd17: sample = -16'sd77;
7'd18: sample = 16'sd22015;
7'd19: sample = 16'sd32619;
7'd20: sample = 16'sd26203;
7'd21: sample = 16'sd6115;
7'd22: sample = -16'sd17165;
7'd23: sample = -16'sd31487;
7'd24: sample = -16'sd29380;
7'd25: sample = -16'sd11943;
7'd26: sample = 16'sd11727;
7'd27: sample = 16'sd29277;
7'd28: sample = 16'sd31551;
7'd29: sample = 16'sd17361;
7'd30: sample = -16'sd5887;
7'd31: sample = -16'sd26064;
7'd32: sample = -16'sd32640;
7'd33: sample = -16'sd22186;
7'd34: sample = -16'sd154;
7'd35: sample = 16'sd21957;
7'd36: sample = 16'sd32612;
7'd37: sample = 16'sd26250;
7'd38: sample = 16'sd6190;
7'd39: sample = -16'sd17099;
7'd40: sample = -16'sd31466;
7'd41: sample = -16'sd29414;
7'd42: sample = -16'sd12014;
7'd43: sample = 16'sd11654;
7'd44: sample = 16'sd29242;
7'd45: sample = 16'sd31571;
7'd46: sample = 16'sd17427;
7'd47: sample = -16'sd5811;
7'd48: sample = -16'sd26017;
7'd49: sample = -16'sd32647;
7'd50: sample = -16'sd22242;
7'd51: sample = -16'sd232;
7'd52: sample = 16'sd21900;
7'd53: sample = 16'sd32604;
7'd54: sample = 16'sd26296;
7'd55: sample = 16'sd6266;
7'd56: sample = -16'sd17033;
7'd57: sample = -16'sd31444;
7'd58: sample = -16'sd29448;
7'd59: sample = -16'sd12086;
7'd60: sample = 16'sd11582;
7'd61: sample = 16'sd29207;
7'd62: sample = 16'sd31592;
7'd63: sample = 16'sd17492;
7'd64: sample = -16'sd5735;
7'd65: sample = -16'sd25970;
7'd66: sample = -16'sd32654;
7'd67: sample = -16'sd22299;
7'd68: sample = -16'sd309;
7'd69: sample = 16'sd21842;
7'd70: sample = 16'sd32596;
7'd71: sample = 16'sd26342;
7'd72: sample = 16'sd6342;
7'd73: sample = -16'sd16967;
7'd74: sample = -16'sd31423;
7'd75: sample = -16'sd29482;
7'd76: sample = -16'sd12158;
7'd77: sample = 16'sd11510;
7'd78: sample = 16'sd29172;
7'd79: sample = 16'sd31612;
7'd80: sample = 16'sd17557;
7'd81: sample = -16'sd5659;
7'd82: sample = -16'sd25923;
7'd83: sample = -16'sd32660;
7'd84: sample = -16'sd22355;
7'd85: sample = -16'sd386;
7'd86: sample = 16'sd21785;
7'd87: sample = 16'sd32588;
7'd88: sample = 16'sd26388;
7'd89: sample = 16'sd6418;
7'd90: sample = -16'sd16901;
7'd91: sample = -16'sd31401;
7'd92: sample = -16'sd29516;
7'd93: sample = -16'sd12230;
7'd94: sample = 16'sd11438;
7'd95: sample = 16'sd29137;
7'd96: sample = 16'sd31633;
7'd97: sample = 16'sd17623;
7'd98: sample = -16'sd5583;
7'd99: sample = -16'sd25875;
7'd100: sample = -16'sd32666;
7'd101: sample = -16'sd22412;
7'd102: sample = -16'sd463;
7'd103: sample = 16'sd21727;
7'd104: sample = 16'sd32580;
7'd105: sample = 16'sd26433;
7'd106: sample = 16'sd6493;
7'd107: sample = -16'sd16835;
7'd108: sample = -16'sd31378;
7'd109: sample = -16'sd29549;
7'd110: sample = -16'sd12301;
7'd111: sample = 16'sd11365;
7'd112: sample = 16'sd29102;
7'd113: sample = 16'sd31653;
7'd114: sample = 16'sd17688;
7'd115: sample = -16'sd5507;
7'd116: sample = -16'sd25828;
7'd117: sample = -16'sd32672;
7'd118: sample = -16'sd22468;
7'd119: sample = -16'sd540;
7'd120: sample = 16'sd21669;
7'd121: sample = 16'sd32572;
7'd122: sample = 16'sd26479;
7'd123: sample = 16'sd6569;
7'd124: sample = -16'sd16768;
7'd125: sample = -16'sd31356;
7'd126: sample = -16'sd29582;
7'd127: sample = -16'sd12373;


            default: sample = 16'sd0;
        endcase
    end
endmodule

verilog/decoder/goertzel.v
module goertzel
  (

    input wire clk,reset,
    output reg signed [15:0] maxcoeff,
    output wire signed [15:0] COEFF_tb,
    output reg signed [63:0] power_tb,
    output reg signed [63:0] max_power,
    output wire signed [63:0] power



  );

  reg [6:0] addr = 7'd0;
  wire signed [15:0] sample;

  localparam integer Fs = 8000;
  localparam integer N  = 128;

  reg signed [15:0] COEFF [0:7];




  initial
  begin
    COEFF[0] = 16'sd28106; // 697 Hz
    COEFF[1] = 16'sd27018; // 770 Hz
    COEFF[2] = 16'sd25330; // 852 Hz
    COEFF[3] = 16'sd24126; // 941 Hz
    COEFF[4] = 16'sd19478; // 1209 Hz
    COEFF[5] = 16'sd16846; // 1336 Hz
    COEFF[6] = 16'sd12490; // 1477 Hz
    COEFF[7] = 16'sd9220;  // 1633 Hz
  end



  reg [2:0] i = 3'd0;
  reg signed [31:0] s1 = 0;
  reg signed [31:0] s2 = 0;

  wire signed [31:0] s_next;
  wire signed [47:0] s1_prod;
  assign s1_prod = COEFF[i] * s1;
  reg [6:0] count = 0;

  assign COEFF_tb=COEFF[i];
  assign s_next = {{16{sample[15]}}, sample} + (s1_prod >>> 14) - s2;

  assign power =
         (s_next * s_next)
         + (s1 * s1)
         - (((COEFF[i] * s_next * s1) >>> 14));

  always @(posedge clk)
  begin

    if(reset)
    begin
      addr      <= 7'd0;
      count     <= 7'd0;
      i         <= 3'd0;
      s1        <= 32'sd0;
      s2        <= 32'sd0;
      max_power <= 64'sd0;
      maxcoeff  <= 16'sd0;
      power_tb  <= 64'sd0;

    end
    else
    begin


      addr <= addr + 1'b1;

      if(count == 7'd127)
      begin
        power_tb<=power;

        if(power>max_power)
        begin
          max_power<=power;
          maxcoeff<=COEFF[i];

        end


        count <= 7'd0;
        s1    <= 32'sd0;
        s2    <= 32'sd0;
        addr  <= 7'd0;

        if (i == 3'd7)
        begin
          i <= 3'd0;
        end
        else
        begin
          i <= i + 1'b1;
        end
      end
      else
      begin

        s2 <= s1;
        s1 <= s_next;

        count <= count + 1'b1;

      end
    end
  end

  sinwave sw(
            .addr(addr),
            .sample(sample)
          );

endmodule

verilog/decoder/testbench.v
// `timescale 1ps/1ps

// module tb_goertzel;

// reg clk;
// reg reset;
// initial begin
//     clk = 0;
//     reset=1;
//     #100
//     reset=0;
//     forever #41667 clk = ~clk;
// end

// wire signed [15:0] maxcoeff;
//     wire signed [63:0] power ;
//     wire signed [63:0] power_tb ;
//     wire signed [63:0] max_power ;
//     wire signed [15:0] COEFF_tb;
// goertzel dut(
// .clk(clk),
//     // .led_amber_n(),
//     // .led_blue_n()
// .reset(reset),
// .maxcoeff(maxcoeff),
// .power(power),
// .power_tb(power_tb),
// .COEFF_tb(COEFF_tb),
// .max_power(max_power)

// );

// integer F;
// initial begin
//     $dumpfile("wave.vcd");
//     $dumpvars(0, tb_goertzel);
// end
// initial begin
//    #90000000;  // 1 us with 1ps timescale
// case(maxcoeff) 
//     16'sd28106 : F = 697;
//     16'sd27018 : F = 770; 
//     16'sd25330 : F = 852;
//     16'sd24126 : F = 941; 
//     16'sd19478 : F = 1209; 
//     16'sd16846 : F = 1336; 
//     16'sd12490 : F = 1477; 
//     16'sd9220  : F = 1633;
//     default    : F = 0; // Highly recommended to avoid uninitialized 'x' values
// endcase
//     $display("final value is %0d %0d",F,maxcoeff);
//     $finish;
    
// end


// initial begin
//     $monitor("Time=%0t power=%0d max_power=%0d coeff=%0d max_coeff=%0d", $time, power_tb,max_power,COEFF_tb, maxcoeff);
// end
// endmodule
`timescale 1ns/1ps

module tb_goertzel;

    reg clk;
    reg reset;
    
    wire signed [15:0] maxcoeff;
    wire signed [63:0] power;
    wire signed [63:0] power_tb;
    wire signed [63:0] max_power;
    wire signed [15:0] COEFF_tb;
    integer F;

    // Instantiate Device Under Test
    goertzel dut (
        .clk(clk),
        .reset(reset),
        .maxcoeff(maxcoeff),
        .power(power),
        .power_tb(power_tb),
        .COEFF_tb(COEFF_tb),
        .max_power(max_power)
    );

    // 12 MHz Clock Generator (Period = 83.333 ns -> Half-Period = 41.667 ns)
    always #41.667 clk = ~clk;

    initial begin
        $dumpfile("wave.vcd");
        $dumpvars(0, tb_goertzel);
        
        // Initialize signals
        clk = 0;
        reset = 1;
        
        // Hold reset for 3 full clock cycles
        #250; 
        reset = 0;
        
        // Print progress monitor directly to the terminal
        $monitor("Time=%0t ns | Bin Index=%0d | Coeff=%0d | Power=%0d | Peak Power Found=%0d", 
                 $time, dut.i, COEFF_tb, power_tb, max_power);
        
        // --- DYNAMIC TERMINATION ---
        // Instead of hardcoding delays, we wait until the design finishes the 
        // 8th frequency bin (index i = 7) and the 128th sample (count = 127).
        @(posedge clk);
        while (dut.i !== 3'd7 || dut.count !== 7'd127) begin
            @(posedge clk);
        end
        
        // Wait 1 final clock cycle to allow the final comparison logic 
        // to update the register outputs (maxcoeff, max_power)
        @(posedge clk);

        // Map the highest recorded coefficient to its corresponding frequency
        case(maxcoeff) 
            16'sd28106 : F = 697;
            16'sd27018 : F = 770; 
            16'sd25330 : F = 852;
            16'sd24126 : F = 941; 
            16'sd19478 : F = 1209;
            16'sd16846 : F = 1336; 
            16'sd12490 : F = 1477; 
            16'sd9220  : F = 1633;
            default    : F = 0;
        endcase

        $display("\n=================================");
        $display("       DETECTION COMPLETE        ");
        $display("=================================");
        $display("Detected Frequency : %0d Hz", F);
        $display("Winning Coefficient: %0d", maxcoeff);
        $display("Peak Calculated Power: %0d", max_power);
        $display("=================================\n");
        
        $finish;
    end

endmodule

verilog/decoder/wave.vcd
$date
	Mon Jun 29 10:26:47 2026
$end
$version
	Icarus Verilog
$end
$timescale
	1ps
$end
$scope module tb_goertzel $end
$var wire 64 ! power_tb [63:0] $end
$var wire 64 " power [63:0] $end
$var wire 16 # maxcoeff [15:0] $end
$var wire 64 $ max_power [63:0] $end
$var wire 16 % COEFF_tb [15:0] $end
$var reg 1 & clk $end
$var reg 1 ' reset $end
$var integer 32 ( F [31:0] $end
$scope module dut $end
$var wire 16 ) COEFF_tb [15:0] $end
$var wire 1 & clk $end
$var wire 1 ' reset $end
$var wire 16 * sample [15:0] $end
$var wire 32 + s_next [31:0] $end
$var wire 48 , s1_prod [47:0] $end
$var wire 64 - power [63:0] $end
$var reg 7 . addr [6:0] $end
$var reg 7 / count [6:0] $end
$var reg 3 0 i [2:0] $end
$var reg 64 1 max_power [63:0] $end
$var reg 16 2 maxcoeff [15:0] $end
$var reg 64 3 power_tb [63:0] $end
$var reg 32 4 s1 [31:0] $end
$var reg 32 5 s2 [31:0] $end
$scope module sw $end
$var wire 7 6 addr [6:0] $end
$var reg 16 7 sample [15:0] $end
$upscope $end
$upscope $end
$upscope $end
$enddefinitions $end
#0
$dumpvars
b0 7
b0 6
b0 5
b0 4
bx 3
bx 2
bx 1
b0 0
b0 /
b0 .
b0 -
b0 ,
b0 +
b0 *
b110110111001010 )
bx (
1'
0&
b110110111001010 %
bx $
bx #
b0 "
bx !
$end
#41667
b0 !
b0 3
b0 #
b0 2
b0 $
b0 1
1&
#83334
0&
#125001
1&
#166668
0&
#208335
1&
#250000
0'
#250002
0&
#291669
b11101000010011010110001000000 "
b11101000010011010110001000000 -
b101011000111000 +
b101011000111000 *
b101011000111000 7
b1 /
b1 .
b1 6
1&
#333336
0&
#375003
b10001001101011001 +
b111111101110010 *
b111111101110010 7
b10 /
b100100111110011110000000110000 ,
b10100110000111001110011001100111 "
b10100110000111001110011001100111 -
b101011000111000 4
b10 .
b10 6
1&
#416670
0&
#458337
b11110100001001101 +
b110011000101101 *
b110011000101101 7
b11 /
b1110110000101100010100100111010 ,
b101000110100101101110111100010111 "
b101000110100101101110111100010111 -
b10001001101011001 4
b101011000111000 5
b11 .
b11 6
1&
#500004
0&
#541671
b100100100111100110 +
b1011110010111 *
b1011110010111 7
b100 /
b11010001011010100001010111000010 ,
b101100011001101000101110110101110 "
b101100011001101000101110110101110 -
b11110100001001101 4
b10001001101011001 5
b100 .
b100 6
1&
#583338
0&
#625005
b11100000101111001 +
b1011110010110010 *
b1011110010110010 7
b101 /
b11111011010001010011110101111100 ,
b101101101011010011101001110010011 "
b101101101011010011101001110010011 -
b100100100111100110 4
b11110100001001101 5
b101 .
b101 6
1&
#666672
0&
#708339
b11111000010001 +
b1000010011101011 *
b1000010011101011 7
b110 /
b11000000110000110010111001111010 ,
b1001101001010001011001111101110100 "
b1001101001010001011001111101110100 -
b11100000101111001 4
b100100100111100110 5
b110 .
b110 6
1&
#750006
0&
#791673
b11111111111111100011011001011101 +
b1000110101011110 *
b1000110101011110 7
b111 /
b11010100111100011011001101010 ,
b1111111111011110010010001001101010 "
b1111111111011110010010001001101010 -
b11111000010001 4
b11100000101111001 5
b111 .
b111 6
1&
#833340
0&
#875007
b11111111111111001000001010000001 +
b1101000110100001 *
b1101000110100001 7
b1000 /
b111111111111111100111011101111000111111001100010 ,
b10010101100100100110100000001000101 "
b10010101100100100110100000001000101 -
b11111111111111100011011001011101 4
b11111000010001 5
b1000 .
b1000 6
1&
#916674
0&
#958341
b11111111111110111111101011111001 +
b10111000010111 *
b10111000010111 7
b1001 /
b111111111111111010000000110011111110011011001010 ,
b10001000101101101010100110010011000 "
b10001000101101101010100110010011000 -
b11111111111111001000001010000001 4
b11111111111111100011011001011101 5
b1001 .
b1001 6
1&
#1000008
0&
#1041675
b11111111111111010000101010111111 +
b111001010000000 *
b111001010000000 7
b1010 /
b111111111111111001000110101100000000110101111010 ,
b10010000010101001001110101011100111 "
b10010000010101001001110101011100111 -
b11111111111110111111101011111001 4
b11111111111111001000001010000001 5
b1010 .
b1010 6
1&
#1083342
0&
#1125009
b11111111111111110110110100101000 +
b111101100101010 *
b111101100101010 7
b1011 /
b111111111111111010111011001111011100110110110110 ,
b11000101011000100010111111010011111 "
b11000101011000100010111111010011111 -
b11111111111111010000101010111111 4
b11111111111110111111101011111001 5
b1011 .
b1011 6
1&
#1166676
0&
#1208343
b100011110011101001 +
b100001110010000 *
b100001110010000 7
b1100 /
b111111111111111111000001000001100010100110010000 ,
b11110001010000110110101010001101011 "
b11110001010000110110101010001101011 -
b11111111111111110110110100101000 4
b11111111111111010000101010111111 5
b1100 .
b1100 6
1&
#1250010
0&
#1291677
b1000101001001011010 +
b1110100010110101 *
b1110100010110101 7
b1101 /
b11110101101100110100010011011010 ,
b11100011000000101000101000111000101 "
b11100011000000101000101000111000101 -
b100011110011101001 4
b11111111111111110110110100101000 5
b1101 .
b1101 6
1&
#1333344
0&
#1375011
b1001100011011111110 +
b1001101000000010 *
b1001101000000010 7
b1110 /
b111011010011110010100110100000100 ,
b11000010101000101001000001110111010 "
b11000010101000101001000001110111010 -
b1000101001001011010 4
b100011110011101001 5
b1110 .
b1110 6
1&
#1416678
0&
#1458345
b110110000000101001 +
b1000000010000111 *
b1000000010000111 7
b1111 /
b1000001100011111110010101001101100 ,
b11010001101101011011110110001101100 "
b11010001101101011011110110001101100 -
b1001100011011111110 4
b1000101001001011010 5
b1111 .
b1111 6
1&
#1500012
0&
#1541679
b1010110011111110 +
b1010100110001111 *
b1010100110001111 7
b10000 /
b101110010100110110101010101011010 ,
b11111110000001110101100010010111001 "
b11111110000001110101100010010111001 -
b110110000000101001 4
b1001100011011111110 5
b10000 .
b10000 6
1&
#1583346
0&
#1625013
b11111111111111011100100001001100 +
b1111111110110011 *
b1111111110110011 7
b10001 /
b1001010001100001010011001101100 ,
b11111110001111011001100110111001101 "
b11111110001111011001100110111001101 -
b1010110011111110 4
b110110000000101001 5
b10001 .
b10001 6
1&
#1666680
0&
#1708347
b11111111111110111101101100100010 +
b101010111111111 *
b101010111111111 7
b10010 /
b111111111111111100001100100010000110011111111000 ,
b11001010011011101001011101000111001 "
b11001010011011101001011101000111001 -
b11111111111111011100100001001100 4
b1010110011111110 5
b10010 .
b10010 6
1&
#1750014
0&
#1791681
b11111111111110111001101101000000 +
b111111101101011 *
b111111101101011 7
b10011 /
b111111111111111000111001000010000110001011010100 ,
b10100111110001101000010000101011000 "
b10100111110001101000010000101011000 -
b11111111111110111101101100100010 4
b11111111111111011100100001001100 5
b10011 .
b10011 6
1&
#1833348
0&
#1875015
b11111111111111010000000111000100 +
b110011001011011 *
b110011001011011 7
b10100 /
b111111111111111000011101101000101100000010000000 ,
b10110110100000000010110011010100001 "
b10110110100000000010110011010100001 -
b11111111111110111001101101000000 4
b11111111111110111101101100100010 5
b10100 .
b10100 6
1&
#1916682
0&
#1958349
b11111111111111110101101000110010 +
b1011111100011 *
b1011111100011 7
b10101 /
b111111111111111010110111011000111101100010101000 ,
b11000001101011110100000001111000111 "
b11000001101011110100000001111000111 -
b11111111111111010000000111000100 4
b11111111111110111001101101000000 5
b10101 .
b10101 6
1&
#2000016
0&
#2041683
b11001111011000000 +
b1011110011110011 *
b1011110011110011 7
b10110 /
b111111111111111110111000111001000111010101110100 ,
b10011011000001001000011110010011110 "
b10011011000001001000011110010011110 -
b11111111111111110101101000110010 4
b11111111111111010000000111000100 5
b10110 .
b10110 6
1&
#2083350
0&
#2125017
b101111001001001011 +
b1000010100000001 *
b1000010100000001 7
b10111 /
b10110001110111110000001110000000 ,
b1100011110000100111001111101100101 "
b1100011110000100111001111101100101 -
b11001111011000000 4
b11111111111111110101101000110010 5
b10111 .
b10111 6
1&
#2166684
0&
#2208351
b101111110001110000 +
b1000110100111100 *
b1000110100111100 7
b11000 /
b101000011011111010001111000101110 ,
b1010000001010011101101111111000000 "
b1010000001010011101101111111000000 -
b101111001001001011 4
b11001111011000000 5
b11000 .
b11000 6
1&
#2250018
0&
#2291685
b11111111001101001 +
b1101000101011001 *
b1101000101011001 7
b11001 /
b101000111110101101110000001100000 ,
b1010101101110000010000111110001100 "
b1010101101110000010000111110001100 -
b101111110001110000 4
b101111001001001011 5
b11001 .
b11001 6
1&
#2333352
0&
#2375019
b1001110011110100 +
b10110111001111 *
b10110111001111 7
b11010 /
b11011010111001010111001111011010 ,
b1001000001000011101111101001110100 "
b1001000001000011101111101001110100 -
b11111111001101001 4
b101111110001110000 5
b11010 .
b11010 6
1&
#2416686
0&
#2458353
b11111111111111111000000100110010 +
b111001001011101 *
b111001001011101 7
b11011 /
b1000011010011111011110010001000 ,
b100100100011001110101101000100111 "
b100100100011001110101101000100111 -
b1001110011110100 4
b11111111001101001 5
b11011 .
b11011 6
1&
#2500020
0&
#2541687
b11111111111111110000010011000011 +
b111101100111111 *
b111101100111111 7
b11100 /
b111111111111111111001001100111100011101101110100 ,
b1011111111001001101011001001001 "
b1011111111001001101011001001001 -
b11111111111111111000000100110010 4
b1001110011110100 5
b11100 .
b11100 6
1&
#2583354
0&
#2625021
b11111111111111110001001110100010 +
b100001111010001 *
b100001111010001 7
b11101 /
b111111111111111110010100010000001100100011011110 ,
b1000010110111101100001011100111 "
b1000010110111101100001011100111 -
b11111111111111110000010011000011 4
b11111111111111111000000100110010 5
b11101 .
b11101 6
1&
#2666688
0&
#2708355
b11111111111111110100111011000011 +
b1110100100000001 *
b1110100100000001 7
b11110 /
b111111111111111110011010101000010111011111010100 ,
b111100001110001100110001011010 "
b111100001110001100110001011010 -
b11111111111111110001001110100010 4
b11111111111111110000010011000011 5
b11110 .
b11110 6
1&
#2750022
0&
#2791689
b11111111111111110101011010000010 +
b1001101000110000 *
b1001101000110000 7
b11111 /
b111111111111111110110011111111010010110011011110 ,
b100001100111111110011101111000 "
b100001100111111110011101111000 -
b11111111111111110100111011000011 4
b11111111111111110001001110100010 5
b11111 .
b11111 6
1&
#2833356
0&
#2875023
b11111111111111110000111011111011 +
b1000000010000000 *
b1000000010000000 7
b100000 /
b111111111111111110110111010011111001110010010100 ,
b1000001011001000001111111110011 "
b1000001011001000001111111110011 -
b11111111111111110101011010000010 4
b11111111111111110100111011000011 5
b100000 .
b100000 6
1&
#2916690
0&
#2958357
b11111111111111101011010101011110 +
b1010100101010110 *
b1010100101010110 7
b100001 /
b111111111111111110011000101000101011000100001110 ,
b1110111111100011011010101011110 "
b1110111111100011011010101011110 -
b11111111111111110000111011111011 4
b11111111111111110101011010000010 5
b100001 .
b100001 6
1&
#3000024
0&
#3041691
b11111111111111101011100100111011 +
b1111111101100110 *
b1111111101100110 7
b100010 /
b111111111111111101110010001101000010001000101100 ,
b1111000001001010111100010100111 "
b1111000001001010111100010100111 -
b11111111111111101011010101011110 4
b11111111111111110000111011111011 5
b100010 .
b100010 6
1&
#3083358
0&
#3125025
b11111111111111110110111111011000 +
b101010111000101 *
b101010111000101 7
b100011 /
b111111111111111101110011110111000100011110001110 ,
b10110110100111110110010010000110 "
b10110110100111110110010010000110 -
b11111111111111101011100100111011 4
b11111111111111101011010101011110 5
b100011 .
b100011 6
1&
#3166692
0&
#3208359
b1100111011011101 +
b111111101100100 *
b111111101100100 7
b100100 /
b111111111111111111000010001011010011100001110000 ,
b111000000001010010101111100111010 "
b111000000001010010101111100111010 -
b11111111111111110110111111011000 4
b11111111111111101011100100111011 5
b100100 .
b100100 6
1&
#3250026
0&
#3291693
b100101100110001111 +
b110011010001010 *
b110011010001010 7
b100101 /
b1011000101101110101001101100010 ,
b1011101010110110010110010000001000 "
b1011101010110110010110010000001000 -
b1100111011011101 4
b11111111111111110110111111011000 5
b100101 .
b100101 6
1&
#3333360
0&
#3375027
b110101000101000011 +
b1100000101110 *
b1100000101110 7
b100110 /
b100000001111111001000110111010110 ,
b1100100111100001011101011101111011 "
b1100100111100001011101011101111011 -
b100101100110001111 4
b1100111011011101 5
b100110 .
b100110 6
1&
#3416694
0&
#3458361
b110001010010000100 +
b1011110100110101 *
b1011110100110101 7
b100111 /
b101101100001101111010010111011110 ,
b1011110110101111011111111010010110 "
b1011110110101111011111111010010110 -
b110101000101000011 4
b100101100110001111 5
b100111 .
b100111 6
1&
#3500028
0&
#3541695
b10111110001111100 +
b1000010100010110 *
b1000010100010110 7
b101000 /
b101010010001010100110010000101000 ,
b1111010111110100100101101101010001 "
b1111010111110100100101101101010001 -
b110001010010000100 4
b110101000101000011 5
b101000 .
b101000 6
1&
#3583362
0&
#3625029
b11111111111111110000010101001010 +
b1000110100011010 *
b1000110100011010 7
b101001 /
b10100011001011010000010111011000 ,
b10110101010010000000011110001010001 "
b10110101010010000000011110001010001 -
b10111110001111100 4
b110001010010000100 5
b101001 .
b101001 6
1&
#3666696
0&
#3708363
b11111111111111001010011010000000 +
b1101000100010010 *
b1101000100010010 7
b101010 /
b111111111111111110010100011110101010111001100100 ,
b11010001101001101011111010111110100 "
b11010001101001101011111010111110100 -
b11111111111111110000010101001010 4
b10111110001111100 5
b101010 .
b101010 6
1&
#3750030
0&
#3791697
b11111111111110110110100100111011 +
b10110110000110 *
b10110110000110 7
b101011 /
b111111111111111010010000001111111110000100000000 ,
b10111101000111001010111111110010010 "
b10111101000111001010111111110010010 -
b11111111111111001010011010000000 4
b11111111111111110000010101001010 5
b101011 .
b101011 6
1&
#3833364
0&
#3875031
b11111111111110111110110001110110 +
b111001000111010 *
b111001000111010 7
b101100 /
b111111111111111000001000001011110010011110001110 ,
b10110010101111000110101100001001001 "
b10110010101111000110101100001001001 -
b11111111111110110110100100111011 4
b11111111111111001010011010000000 5
b101100 .
b101100 6
1&
#3916698
0&
#3958365
b11111111111111100001001111110011 +
b111101101010011 *
b111101101010011 7
b101101 /
b111111111111111001000000011101101101001100011100 ,
b11011011110110001100100111000011000 "
b11011011110110001100100111000011000 -
b11111111111110111110110001110110 4
b11111111111110110110100100111011 5
b101101 .
b101101 6
1&
#4000032
0&
#4041699
b10000101110000101 +
b100010000010011 *
b100010000010011 7
b101110 /
b111111111111111100101100111110100011010010111110 ,
b100000111011011000110101111111000100 "
b100000111011011000110101111111000100 -
b11111111111111100001001111110011 4
b11111111111110111110110001110110 5
b101110 .
b101110 6
1&
#4083366
0&
#4125033
b111010000001000100 +
b1110100101001101 *
b1110100101001101 7
b101111 /
b1110010101110101011011111110010 ,
b11110111101011011100111001110010001 "
b11110111101011011100111001110010001 -
b10000101110000101 4
b11111111111111100001001111110011 5
b101111 .
b101111 6
1&
#4166700
0&
#4208367
b1001100011100111111 +
b1001101001011111 *
b1001101001011111 7
b110000 /
b110001110000110010110100110101000 ,
b11001000010000000101001001110000111 "
b11001000010000000101001001110000111 -
b111010000001000100 4
b10000101110000101 5
b110000 .
b110000 6
1&
#4250034
0&
#4291701
b1000001001010100001 +
b1000000001111001 *
b1000000001111001 7
b110001 /
b1000001100100110110000101010110110 ,
b11000001001000010100000111001011000 "
b11000001001000010100000111001011000 -
b1001100011100111111 4
b111010000001000100 5
b110001 .
b110001 6
1&
#4333368
0&
#4375035
b11101111001110100 +
b1010100100011110 *
b1010100100011110 7
b110010 /
b110111111001001010100000000001010 ,
b11100000101110011111100010000000011 "
b11100000101110011111100010000000011 -
b1000001001010100001 4
b1001100011100111111 5
b110010 .
b110010 6
1&
#4416702
0&
#4458369
b11111111111111110010000100111010 +
b1111111100011000 *
b1111111100011000 7
b110011 /
b11001101001100001110101110001000 ,
b11100001010010011011110011000001101 "
b11100001010010011011110011000001101 -
b11101111001110100 4
b1000001001010100001 5
b110011 .
b110011 6
1&
#4500036
0&
#4541703
b11111111111111001111100011101111 +
b101010110001100 *
b101010110001100 7
b110100 /
b111111111111111110100000011101011110100111000100 ,
b10101100111011011100110101001011001 "
b10101100111011011100110101001011001 -
b11111111111111110010000100111010 4
b11101111001110100 5
b110100 .
b110100 6
1&
#4583370
0&
#4625037
b11111111111111000010110010001010 +
b111111101011100 *
b111111101011100 7
b110101 /
b111111111111111010110011100110100010111110010110 ,
b1111101110111111010101110110111000 "
b1111101110111111010101110110111000 -
b11111111111111001111100011101111 4
b11111111111111110010000100111010 5
b110101 .
b110101 6
1&
#4666704
0&
#4708371
b11111111111111001101110110010000 +
b110011010111000 *
b110011010111000 7
b110110 /
b111111111111111001011011111100011110011011100100 ,
b1111100100000000011110100000010010 "
b1111100100000000011110100000010010 -
b11111111111111000010110010001010 4
b11111111111111001111100011101111 5
b110110 .
b110110 6
1&
#4750038
0&
#4791705
b11111111111111101000101101100100 +
b1100001111010 *
b1100001111010 7
b110111 /
b111111111111111010100111110111010010001110100000 ,
b10000011110000001100011101000101001 "
b10000011110000001100011101000101001 -
b11111111111111001101110110010000 4
b11111111111111000010110010001010 5
b110111 .
b110111 6
1&
#4833372
0&
#4875039
b110000010110101 +
b1011110101110111 *
b1011110101110111 7
b111000 /
b111111111111111101100000001100111001000011101000 ,
b1100110100010101001001001111011000 "
b1100110100010101001001001111011000 -
b11111111111111101000101101100100 4
b11111111111111001101110110010000 5
b111000 .
b111000 6
1&
#4916706
0&
#4958373
b11001111110101101 +
b1000010100101100 *
b1000010100101100 7
b111001 /
b101001011110010101111111010010 ,
b110111010000110110111010101110110 "
b110111010000110110111010101110110 -
b110000010110101 4
b11111111111111101000101101100100 5
b111001 .
b111001 6
1&
#5000040
0&
#5041707
b11111010101010101 +
b1000110011111000 *
b1000110011111000 7
b111010 /
b10110010010001001010011110000010 ,
b100000100010010011111011010101110 "
b100000100010010011111011010101110 -
b11001111110101101 4
b110000010110101 5
b111010 .
b111010 6
1&
#5083374
0&
#5125041
b11000110100100000 +
b1101000011001010 *
b1101000011001010 7
b111011 /
b11010111000000001100011000010010 ,
b100000111101101011100010100101111 "
b100000111101101011100010100101111 -
b11111010101010101 4
b11001111110101101 5
b111011 .
b111011 6
1&
#5166708
0&
#5208375
b1110000100101000 +
b10110100111110 *
b10110100111110 7
b111100 /
b10101010010011111111101101000000 ,
b11010110111001111111100011110110 "
b11010110111001111111100011110110 -
b11000110100100000 4
b11111010101010101 5
b111100 .
b111100 6
1&
#5250042
0&
#5291709
b110011100110101 +
b111001000010111 *
b111001000010111 7
b111101 /
b1100000100011111011000110010000 ,
b1010011111010111100111001110111 "
b1010011111010111100111001110111 -
b1110000100101000 4
b11000110100100000 5
b111101 .
b111101 6
1&
#5333376
0&
#5375043
b100101101001100 +
b111101101101000 *
b111101101101000 7
b111110 /
b101100010000110000000011010010 ,
b1011101011100011101100000010 "
b1011101011100011101100000010 -
b110011100110101 4
b1110000100101000 5
b111110 .
b111110 6
1&
#5416710
0&
#5458377
b101111001001010 +
b100010001010100 *
b100010001010100 7
b111111 /
b100000010010101100010111111000 ,
b1001010011001110001010111011 "
b1001010011001110001010111011 -
b100101101001100 4
b110011100110101 5
b111111 .
b111111 6
1&
#5500044
0&
#5541711
b100000000001100 +
b1110100110011001 *
b1110100110011001 7
b1000000 /
b101000011011111110100001100100 ,
b1010010010001111000010010101 "
b1010010010001111000010010101 -
b101111001001010 4
b100101101001100 5
b1000000 .
b1000000 6
1&
#5583378
0&
#5625045
b11111111111111111010101000100010 +
b1001101010001110 *
b1001101010001110 7
b1000001 /
b11011011101111010010101111000 ,
b1010001101011010101101111011110 "
b1010001101011010101101111011110 -
b100000000001100 4
b101111001001010 5
b1000001 .
b1000001 6
1&
#5666712
0&
#5708379
b11111111111111101010110100011000 +
b1000000001110010 *
b1000000001110010 7
b1000010 /
b111111111111111111011011001011001011100011010100 ,
b100011010011101010101000100000010 "
b100011010011101010101000100000010 -
b11111111111111111010101000100010 4
b100000000001100 5
b1000010 .
b1000010 6
1&
#5750046
0&
