verilog/decoder/sinwave.v
module sinwave (
    input  wire [6:0] addr,
    output reg signed [15:0] sample
);
    always @(*) begin
        case (addr)
7'd0: sample = 16'sd0;
7'd1: sample = 16'sd30041;
7'd2: sample = 16'sd23992;
7'd3: sample = -16'sd10881;
7'd4: sample = -16'sd32681;
7'd5: sample = -16'sd15219;
7'd6: sample = 16'sd20527;
7'd7: sample = 16'sd31612;
7'd8: sample = 16'sd4719;
7'd9: sample = -16'sd27844;
7'd10: sample = -16'sd26955;
7'd11: sample = 16'sd6317;
7'd12: sample = 16'sd32000;
7'd13: sample = 16'sd19239;
7'd14: sample = -16'sd16635;
7'd15: sample = -16'sd32524;
7'd16: sample = -16'sd9339;
7'd17: sample = 16'sd25066;
7'd18: sample = 16'sd29357;
7'd19: sample = -16'sd1621;
7'd20: sample = -16'sd30652;
7'd21: sample = -16'sd22858;
7'd22: sample = 16'sd12397;
7'd23: sample = 16'sd32759;
7'd24: sample = 16'sd13765;
7'd25: sample = -16'sd21766;
7'd26: sample = -16'sd31147;
7'd27: sample = -16'sd3109;
7'd28: sample = 16'sd28664;
7'd29: sample = 16'sd26001;
7'd30: sample = -16'sd7899;
7'd31: sample = -16'sd32310;
7'd32: sample = -16'sd17904;
7'd33: sample = 16'sd18011;
7'd34: sample = 16'sd32288;
7'd35: sample = 16'sd7774;
7'd36: sample = -16'sd26079;
7'd37: sample = -16'sd28602;
7'd38: sample = 16'sd3237;
7'd39: sample = 16'sd31187;
7'd40: sample = 16'sd21669;
7'd41: sample = -16'sd13882;
7'd42: sample = -16'sd32755;
7'd43: sample = -16'sd12277;
7'd44: sample = 16'sd22950;
7'd45: sample = 16'sd30606;
7'd46: sample = 16'sd1492;
7'd47: sample = -16'sd29414;
7'd48: sample = -16'sd24983;
7'd49: sample = 16'sd9462;
7'd50: sample = 16'sd32540;
7'd51: sample = 16'sd16524;
7'd52: sample = -16'sd19343;
7'd53: sample = -16'sd31972;
7'd54: sample = -16'sd6190;
7'd55: sample = 16'sd27028;
7'd56: sample = 16'sd27776;
7'd57: sample = -16'sd4846;
7'd58: sample = -16'sd31646;
7'd59: sample = -16'sd20427;
7'd60: sample = 16'sd15333;
7'd61: sample = 16'sd32672;
7'd62: sample = 16'sd10760;
7'd63: sample = -16'sd24079;
7'd64: sample = -16'sd29990;
7'd65: sample = 16'sd129;
7'd66: sample = 16'sd30092;
7'd67: sample = 16'sd23904;
7'd68: sample = -16'sd11003;
7'd69: sample = -16'sd32691;
7'd70: sample = -16'sd15105;
7'd71: sample = 16'sd20628;
7'd72: sample = 16'sd31578;
7'd73: sample = 16'sd4591;
7'd74: sample = -16'sd27912;
7'd75: sample = -16'sd26882;
7'd76: sample = 16'sd6443;
7'd77: sample = 16'sd32028;
7'd78: sample = 16'sd19135;
7'd79: sample = -16'sd16746;
7'd80: sample = -16'sd32509;
7'd81: sample = -16'sd9216;
7'd82: sample = 16'sd25149;
7'd83: sample = 16'sd29300;
7'd84: sample = -16'sd1749;
7'd85: sample = -16'sd30697;
7'd86: sample = -16'sd22766;
7'd87: sample = 16'sd12516;
7'd88: sample = 16'sd32761;
7'd89: sample = 16'sd13648;
7'd90: sample = -16'sd21862;
7'd91: sample = -16'sd31107;
7'd92: sample = -16'sd2981;
7'd93: sample = 16'sd28726;
7'd94: sample = 16'sd25923;
7'd95: sample = -16'sd8024;
7'd96: sample = -16'sd32331;
7'd97: sample = -16'sd17796;
7'd98: sample = 16'sd18119;
7'd99: sample = 16'sd32266;
7'd100: sample = 16'sd7649;
7'd101: sample = -16'sd26157;
7'd102: sample = -16'sd28539;
7'd103: sample = 16'sd3365;
7'd104: sample = 16'sd31226;
7'd105: sample = 16'sd21573;
7'd106: sample = -16'sd13998;
7'd107: sample = -16'sd32752;
7'd108: sample = -16'sd12158;
7'd109: sample = 16'sd23042;
7'd110: sample = 16'sd30560;
7'd111: sample = 16'sd1364;
7'd112: sample = -16'sd29471;
7'd113: sample = -16'sd24900;
7'd114: sample = 16'sd9586;
7'd115: sample = 16'sd32555;
7'd116: sample = 16'sd16413;
7'd117: sample = -16'sd19447;
7'd118: sample = -16'sd31944;
7'd119: sample = -16'sd6064;
7'd120: sample = 16'sd27101;
7'd121: sample = 16'sd27707;
7'd122: sample = -16'sd4973;
7'd123: sample = -16'sd31679;
7'd124: sample = -16'sd20326;
7'd125: sample = 16'sd15446;
7'd126: sample = 16'sd32662;
7'd127: sample = 16'sd10638;

            default: sample = 16'sd0;
        endcase
    end
endmodule

verilog/decoder/goertzel.v
// module goertzel
// (

//     input wire clk,reset,
// output reg signed [15:0] maxcoeff,
// output wire signed [15:0] COEFF_tb,
//     output reg signed [63:0] power_tb,
//     output reg signed [63:0] max_power,
//     output wire signed [63:0] power
// );

// reg [6:0] addr = 7'd0;
// wire signed [15:0] sample;

// localparam integer Fs = 8000;
// localparam integer N  = 128;
// localparam signed [15:0] COEFFF =
//     (F == 697)  ? 16'sd28106 :
//     (F == 770)  ? 16'sd27018 :
//     (F == 852)  ? 16'sd25330 :
//     (F == 941)  ? 16'sd24126 :
//     (F == 1209) ? 16'sd19478 :
//     (F == 1336) ? 16'sd16846 :
//     (F == 1477) ? 16'sd12490 :
//     (F == 1633) ? 16'sd9220  :
//                   16'sd28106;

// reg signed [15:0] COEFF [0:7];

// // Fixed: Correctly initialize the array inside an initial block

// always @(*) begin
  
//     if(reset) begin
//         max_power=0;
//         maxcoeff=0;
//         count = 0;
//         s1 = 0;
//         s2 = 0;
//         addr = 0;

//     end

// end 

// initial begin
//     COEFF[0] = 16'sd28106; // 697 Hz
//     COEFF[1] = 16'sd27018; // 770 Hz
//     COEFF[2] = 16'sd25330; // 852 Hz
//     COEFF[3] = 16'sd24126; // 941 Hz
//     COEFF[4] = 16'sd19478; // 1209 Hz
//     COEFF[5] = 16'sd16846; // 1336 Hz
//     COEFF[6] = 16'sd12490; // 1477 Hz
//     COEFF[7] = 16'sd9220;  // 1633 Hz
// end
// // Add this inside module goertzel

// reg [2:0] i = 3'd0;
// reg signed [31:0] s1 = 0;
// reg signed [31:0] s2 = 0;

// wire signed [31:0] s_next;

// reg [6:0] count = 0;

// assign COEFF_tb=COEFF[i];
// assign s_next =
//       {{16{sample[15]}}, sample}
//     + ((COEFF[i] * s1) >>> 14)
//     - s2;

// assign power =
//               (s_next * s_next)
//             + (s1 * s1)
//             - (((COEFF[i] * s_next * s1) >>> 14));


// always @(posedge clk) begin
  
//     if(count == 7'd127) power_tb<=power;

// end


// always @(*) begin
  
//         if(power>max_power) begin
//           max_power=power;
//           maxcoeff=COEFF[i];

//         end
//         else begin
          
//           max_power=max_power;
//           maxcoeff=maxcoeff;
          
//         end

// end




// always @(posedge clk) begin

//     addr <= addr + 1'b1;

//     if(count == 7'd127) begin



//         count <= 0;
//         s1 <= 0;
//         s2 <= 0;
//         addr <= 0;

//        if (i == 7) begin
//             i <= 0;
//         end else begin
//             i <= i + 1'b1;
//         end
//     end
//     else begin

//         s2 <= s1;
//         s1 <= s_next;

//         count <= count + 1'b1;

//     end
// end

// sinwave sw(
//     .addr(addr),
//     .sample(sample)
// );

// endmodule
module goertzel (
    input wire clk,
    input wire reset,
    output reg signed [15:0] maxcoeff,
    output wire signed [15:0] COEFF_tb,
    output reg signed [63:0] power_tb,
    output reg signed [63:0] max_power,
    output wire signed [63:0] power
);

    reg [6:0] addr = 7'd0;
    wire signed [15:0] sample;
    reg [2:0] i = 3'd0;
    reg signed [31:0] s1 = 32'sd0;
    reg signed [31:0] s2 = 32'sd0;
    reg [6:0] count = 7'd0;

    // DTMF Coefficients Array
    reg signed [15:0] COEFF [0:7];
    initial begin
        COEFF[0] = 16'sd28106; // 697 Hz
        COEFF[1] = 16'sd27018; // 770 Hz
        COEFF[2] = 16'sd25330; // 852 Hz
        COEFF[3] = 16'sd24126; // 941 Hz
        COEFF[4] = 16'sd19478; // 1209 Hz
        COEFF[5] = 16'sd16846; // 1336 Hz
        COEFF[6] = 16'sd12490; // 1477 Hz
        COEFF[7] = 16'sd9220;  // 1633 Hz
    end

    assign COEFF_tb = COEFF[i];

    // Goertzel state update equation
    wire signed [31:0] s_next;
    
    // --- THE FIXED LINE ---
    // Perform multiplication in 48-bit signed width to completely prevent 32-bit intermediate overflow
    wire signed [47:0] s1_prod;
    assign s1_prod = COEFF[i] * s1;
    assign s_next = {{16{sample[15]}}, sample} + (s1_prod >>> 14) - s2;

    // Scale intermediate variables down by 4 bits to prevent overflow during multiplication
    wire signed [63:0] s_next_scaled = s_next >>> 4;
    wire signed [63:0] s1_scaled     = s1 >>> 4;

    // Power calculation
    assign power = (s_next_scaled * s_next_scaled) 
                 + (s1_scaled * s1_scaled) 
                 - (((COEFF[i] * s_next_scaled * s1_scaled) >>> 14));

    // Synchronous controller
    always @(posedge clk) begin
        if (reset) begin
            addr      <= 7'd0;
            count     <= 7'd0;
            i         <= 3'd0;
            s1        <= 32'sd0;
            s2        <= 32'sd0;
            max_power <= 64'sd0;
            maxcoeff  <= 16'sd0;
            power_tb  <= 64'sd0;
        end else begin
            addr <= addr + 1'b1;

            if (count == 7'd127) begin
                power_tb <= power;
                
                // Track peak strictly on the clock edge
                if (power > max_power) begin
                    max_power <= power;
                    maxcoeff  <= COEFF[i];
                end

                // Reset step accumulation
                count <= 7'd0;
                s1    <= 32'sd0;
                s2    <= 32'sd0;
                addr  <= 7'd0;

                // Move to the next coefficient block
                if (i == 3'd7) begin
                    i <= 3'd0;
                end else begin
                    i <= i + 1'b1;
                end
            end else begin
                s2    <= s1;
                s1    <= s_next;
                count <= count + 1'b1;
            end
        end
    end

    // Rom Instantiation
    sinwave sw (
        .addr(addr),
        .sample(sample)
    );

endmodule

verilog/decoder/testbench.v
// `timescale 1ps/1ps

// module tb_goertzel;

// reg clk;
// reg reset;
// initial begin
//     clk = 0;
//     reset=1;
//     #100
//     reset=0;
//     forever #41667 clk = ~clk;
// end

// wire signed [15:0] maxcoeff;
//     wire signed [63:0] power ;
//     wire signed [63:0] power_tb ;
//     wire signed [63:0] max_power ;
//     wire signed [15:0] COEFF_tb;
// goertzel dut(
// .clk(clk),
//     // .led_amber_n(),
//     // .led_blue_n()
// .reset(reset),
// .maxcoeff(maxcoeff),
// .power(power),
// .power_tb(power_tb),
// .COEFF_tb(COEFF_tb),
// .max_power(max_power)

// );

// integer F;
// initial begin
//     $dumpfile("wave.vcd");
//     $dumpvars(0, tb_goertzel);
// end
// initial begin
//    #90000000;  // 1 us with 1ps timescale
// case(maxcoeff) 
//     16'sd28106 : F = 697;
//     16'sd27018 : F = 770; 
//     16'sd25330 : F = 852;
//     16'sd24126 : F = 941; 
//     16'sd19478 : F = 1209; 
//     16'sd16846 : F = 1336; 
//     16'sd12490 : F = 1477; 
//     16'sd9220  : F = 1633;
//     default    : F = 0; // Highly recommended to avoid uninitialized 'x' values
// endcase
//     $display("final value is %0d %0d",F,maxcoeff);
//     $finish;
    
// end


// initial begin
//     $monitor("Time=%0t power=%0d max_power=%0d coeff=%0d max_coeff=%0d", $time, power_tb,max_power,COEFF_tb, maxcoeff);
// end
// endmodule
`timescale 1ns/1ps

module tb_goertzel;

    reg clk;
    reg reset;
    
    wire signed [15:0] maxcoeff;
    wire signed [63:0] power;
    wire signed [63:0] power_tb;
    wire signed [63:0] max_power;
    wire signed [15:0] COEFF_tb;
    integer F;

    // Instantiate Device Under Test
    goertzel dut (
        .clk(clk),
        .reset(reset),
        .maxcoeff(maxcoeff),
        .power(power),
        .power_tb(power_tb),
        .COEFF_tb(COEFF_tb),
        .max_power(max_power)
    );

    // 12 MHz Clock Generator (Period = 83.333 ns -> Half-Period = 41.667 ns)
    always #41.667 clk = ~clk;

    initial begin
        $dumpfile("wave.vcd");
        $dumpvars(0, tb_goertzel);
        
        // Initialize signals
        clk = 0;
        reset = 1;
        
        // Hold reset for 3 full clock cycles
        #250; 
        reset = 0;
        
        // Print progress monitor directly to the terminal
        $monitor("Time=%0t ns | Bin Index=%0d | Coeff=%0d | Power=%0d | Peak Power Found=%0d", 
                 $time, dut.i, COEFF_tb, power_tb, max_power);
        
        // --- DYNAMIC TERMINATION ---
        // Instead of hardcoding delays, we wait until the design finishes the 
        // 8th frequency bin (index i = 7) and the 128th sample (count = 127).
        @(posedge clk);
        while (dut.i !== 3'd7 || dut.count !== 7'd127) begin
            @(posedge clk);
        end
        
        // Wait 1 final clock cycle to allow the final comparison logic 
        // to update the register outputs (maxcoeff, max_power)
        @(posedge clk);

        // Map the highest recorded coefficient to its corresponding frequency
        case(maxcoeff) 
            16'sd28106 : F = 697;
            16'sd27018 : F = 770; 
            16'sd25330 : F = 852;
            16'sd24126 : F = 941; 
            16'sd19478 : F = 1209;
            16'sd16846 : F = 1336; 
            16'sd12490 : F = 1477; 
            16'sd9220  : F = 1633;
            default    : F = 0;
        endcase

        $display("\n=================================");
        $display("       DETECTION COMPLETE        ");
        $display("=================================");
        $display("Detected Frequency : %0d Hz", F);
        $display("Winning Coefficient: %0d", maxcoeff);
        $display("Peak Calculated Power: %0d", max_power);
        $display("=================================\n");
        
        $finish;
    end

endmodule

verilog/decoder/wave.vcd
$date
	Sat Jun 27 18:54:00 2026
$end
$version
	Icarus Verilog
$end
$timescale
	1ps
$end
$scope module tb_goertzel $end
$var wire 64 ! power_tb [63:0] $end
$var wire 64 " power [63:0] $end
$var wire 16 # maxcoeff [15:0] $end
$var wire 64 $ max_power [63:0] $end
$var wire 16 % COEFF_tb [15:0] $end
$var reg 1 & clk $end
$var reg 1 ' reset $end
$var integer 32 ( F [31:0] $end
$scope module dut $end
$var wire 16 ) COEFF_tb [15:0] $end
$var wire 1 & clk $end
$var wire 1 ' reset $end
$var wire 16 * sample [15:0] $end
$var wire 64 + s_next_scaled [63:0] $end
$var wire 32 , s_next [31:0] $end
$var wire 64 - s1_scaled [63:0] $end
$var wire 48 . s1_prod [47:0] $end
$var wire 64 / power [63:0] $end
$var reg 7 0 addr [6:0] $end
$var reg 7 1 count [6:0] $end
$var reg 3 2 i [2:0] $end
$var reg 64 3 max_power [63:0] $end
$var reg 16 4 maxcoeff [15:0] $end
$var reg 64 5 power_tb [63:0] $end
$var reg 32 6 s1 [31:0] $end
$var reg 32 7 s2 [31:0] $end
$scope module sw $end
$var wire 7 8 addr [6:0] $end
$var reg 16 9 sample [15:0] $end
$upscope $end
$upscope $end
$upscope $end
$enddefinitions $end
#0
$dumpvars
b0 9
b0 8
b0 7
b0 6
bx 5
bx 4
bx 3
b0 2
b0 1
b0 0
b0 /
b0 .
b0 -
b0 ,
b0 +
b0 *
b110110111001010 )
bx (
1'
0&
b110110111001010 %
bx $
bx #
b0 "
bx !
$end
#41667
b0 !
b0 5
b0 #
b0 4
b0 $
b0 3
1&
#83334
0&
#125001
1&
#166668
0&
#208335
1&
#250000
0'
#250002
0&
#291669
b1101011100001000111001 "
b1101011100001000111001 /
b11101010101 +
b111010101011001 ,
b111010101011001 *
b111010101011001 9
b1 1
b1 0
b1 8
1&
#333336
0&
#375003
b1001001110000 +
b10010011100000101 ,
b101000011100110000101111 "
b101000011100110000101111 /
b11101010101 -
b101110110111000 *
b101110110111000 9
b10 1
b110010010100110111110100111010 .
b111010101011001 6
b10 0
b10 8
1&
#416670
0&
#458337
b1010110100011 +
b11110111011111110000000 "
b11110111011111110000000 /
b1001001110000 -
b10101101000111101 ,
b1101010101111111 *
b1101010101111111 9
b11 1
b1111110100001011110101011110010 .
b10010011100000101 6
b111010101011001 7
b11 0
b11 8
1&
#500004
0&
#541671
b101010110100 +
b101110010111000001010011 "
b101110010111000001010011 /
b1010110100011 -
b1010101101000110 ,
b1000000001010111 *
b1000000001010111 9
b100 1
b10010100011111010010110100100010 .
b10101101000111101 6
b10010011100000101 7
b100 0
b100 8
1&
#583338
0&
#625005
b1111111111111111111111111111111111111111111111111111100100000001 +
b1001000111111010010011110 "
b1001000111111010010011110 /
b101010110100 -
b11111111111111111001000000011111 ,
b1100010010001101 *
b1100010010001101 9
b101 1
b1001001011100111111001100111100 .
b1010101101000110 6
b10101101000111101 7
b101 0
b101 8
1&
#666672
0&
#708339
b1111111111111111111111111111111111111111111111111110111001001111 +
b100101011001101110110001 "
b100101011001101110110001 /
b1111111111111111111111111111111111111111111111111111100100000001 -
b11111111111111101110010011111100 ,
b101000000101111 *
b101000000101111 9
b110 1
b111111111111111111010000000001001110101101110110 .
b11111111111111111001000000011111 6
b1010101101000110 7
b110 0
b110 8
1&
#750006
0&
#791673
b1111111111111111111111111111111111111111111111111111000001011101 +
b10100101110111111110000 "
b10100101110111111110000 /
b1111111111111111111111111111111111111111111111111110111001001111 -
b11111111111111110000010111011100 ,
b111101101111100 *
b111101101111100 9
b111 1
b111111111111111110000110100111111111101011011000 .
b11111111111111101110010011111100 6
b11111111111111111001000000011111 7
b111 0
b111 8
1&
#833340
0&
#875007
b1111111111111111111111111111111111111111111111111111100000000101 +
b10111100010000001001110 "
b10111100010000001001110 /
b1111111111111111111111111111111111111111111111111111000001011101 -
b11111111111111111000000001011000 ,
b1001001101111 *
b1001001101111 9
b1000 1
b111111111111111110010100101110010100101110011000 .
b11111111111111110000010111011100 6
b11111111111111101110010011111100 7
b1000 0
b1000 8
1&
#916674
0&
#958341
b1111111111111111111111111111111111111111111111111111101100100110 +
b101001100111010011010 "
b101001100111010011010 /
b1111111111111111111111111111111111111111111111111111100000000101 -
b11111111111111111011001001100010 ,
b1001001100111100 *
b1001001100111100 9
b1001 1
b111111111111111111001001010000001011110101110000 .
b11111111111111111000000001011000 6
b11111111111111110000010111011100 7
b1001 0
b1001 8
1&
#1000008
0&
#1041675
b1111111111111111111111111111111111111111111111111111100100010011 +
b11011101110100000110 "
b11011101110100000110 /
b1111111111111111111111111111111111111111111111111111101100100110 -
b11111111111111111001000100110110 ,
b1001011010110101 *
b1001011010110101 9
b1010 1
b111111111111111111011110101101100111101101010100 .
b11111111111111111011001001100010 6
b11111111111111111000000001011000 7
b1010 0
b1010 8
1&
#1083342
0&
#1125009
b1111111111111111111111111111111111111111111111111111101010000011 +
b11001110000111010111 "
b11001110000111010111 /
b1111111111111111111111111111111111111111111111111111100100010011 -
b11111111111111111010100000111101 ,
b1100010101101 *
b1100010101101 9
b1011 1
b111111111111111111010000011111001001001010011100 .
b11111111111111111001000100110110 6
b11111111111111111011001001100010 7
b1011 0
b1011 8
1&
#1166676
0&
#1208343
b10101010011 +
b11011001001100001110011 "
b11011001001100001110011 /
b1111111111111111111111111111111111111111111111111111101010000011 -
b101010100111100 ,
b111110100000000 *
b111110100000000 9
b1100 1
b111111111111111111011010010111001011100100100010 .
b11111111111111111010100000111101 6
b11111111111111111001000100110110 7
b1100 0
b1100 8
1&
#1250010
0&
#1291677
b1001101010010 +
b111000010010100100011111 "
b111000010010100100011111 /
b10101010011 -
b10011010100100001 ,
b100101100100111 *
b100101100100111 9
b1101 1
b100100100011011100110101011000 .
b101010100111100 6
b11111111111111111010100000111101 7
b1101 0
b1101 8
1&
#1333344
0&
#1375011
b1011111000001 +
b100101100011111010000110 "
b100101100011111010000110 /
b1001101010010 -
b10111110000010100 ,
b1011111100000101 *
b1011111100000101 9
b1110 1
b10000100100100101111100100001010 .
b10011010100100001 6
b101010100111100 7
b1110 0
b1110 8
1&
#1416678
0&
#1458345
b110101111101 +
b110001001000110100101000 "
b110001001000110100101000 /
b1011111000001 -
b1101011111010100 ,
b1000000011110100 *
b1000000011110100 9
b1111 1
b10100011000000000110101111001000 .
b10111110000010100 6
b10011010100100001 7
b1111 0
b1111 8
1&
#1500012
0&
#1541679
b1111111111111111111111111111111111111111111111111111110100011010 +
b1000000010110011001110111 "
b1000000010110011001110111 /
b110101111101 -
b11111111111111111101000110101111 ,
b1101101110000101 *
b1101101110000101 9
b10000 1
b1011100100011111001000101001000 .
b1101011111010100 6
b10111110000010100 7
b10000 0
b10000 8
1&
#1583346
0&
#1625013
b1111111111111111111111111111111111111111111111111111001110101010 +
b11000110011110110000111 "
b11000110011110110000111 /
b1111111111111111111111111111111111111111111111111111110100011010 -
b11111111111111110011101010100001 ,
b110000111101010 *
b110000111101010 9
b10001 1
b111111111111111111101100001000101111011100010110 .
b11111111111111111101000110101111 6
b1101011111010100 7
b10001 0
b10001 8
1&
#1666680
0&
#1708347
b1111111111111111111111111111111111111111111111111111010011100110 +
b1010000111110111100010 "
b1010000111110111100010 /
b1111111111111111111111111111111111111111111111111111001110101010 -
b11111111111111110100111001101001 ,
b111001010101101 *
b111001010101101 9
b10010 1
b111111111111111110101011010110101101000000001010 .
b11111111111111110011101010100001 6
b11111111111111111101000110101111 7
b10010 0
b10010 8
1&
#1750014
0&
#1791681
b1111111111111111111111111111111111111111111111111111100011100110 +
b1001100110111011100100 "
b1001100110111011100100 /
b1111111111111111111111111111111111111111111111111111010011100110 -
b11111111111111111000111001100100 ,
b1111100110101011 *
b1111100110101011 9
b10011 1
b111111111111111110110011110101101001001111011010 .
b11111111111111110100111001101001 6
b11111111111111110011101010100001 7
b10011 0
b10011 8
1&
#1833348
0&
#1875015
b1111111111111111111111111111111111111111111111111111011101101111 +
b100110111010011000010 "
b100110111010011000010 /
b1111111111111111111111111111111111111111111111111111100011100110 -
b11111111111111110111011011110110 ,
b1000100001000100 *
b1000100001000100 9
b10100 1
b111111111111111111001111010001101110111011101000 .
b11111111111111111000111001100100 6
b11111111111111110100111001101001 7
b10100 0
b10100 8
1&
#1916682
0&
#1958349
b1111111111111111111111111111111111111111111111111111001011010011 +
b1101010101110011011111 "
b1101010101110011011111 /
b1111111111111111111111111111111111111111111111111111011101101111 -
b11111111111111110010110100111100 ,
b1010011010110110 *
b1010011010110110 9
b10101 1
b111111111111111111000101001110101001110000011100 .
b11111111111111110111011011110110 6
b11111111111111111000111001100100 7
b10101 0
b10101 8
1&
#2000016
0&
#2041683
b1111111111111111111111111111111111111111111111111111010011111110 +
b1011011111100000111011 "
b1011011111100000111011 /
b1111111111111111111111111111111111111111111111111111001011010011 -
b11111111111111110100111111100111 ,
b11000001101101 *
b11000001101101 9
b10110 1
b111111111111111110100101100111000011110101011000 .
b11111111111111110010110100111100 6
b11111111111111110111011011110110 7
b10110 0
b10110 8
1&
#2083350
0&
#2125017
b1001001010 +
b101010011010001100010100 "
b101010011010001100010100 /
b1111111111111111111111111111111111111111111111111111010011111110 -
b10010010100100 ,
b111111111110111 *
b111111111110111 9
b10111 1
b111111111111111110110100011110100110011101000110 .
b11111111111111110100111111100111 6
b11111111111111110010110100111100 7
b10111 0
b10111 8
1&
#2166684
0&
#2208351
b1001001001011 +
b1000011000000101000111111 "
b1000011000000101000111111 /
b1001001010 -
b10010010010111000 ,
b11010111000101 *
b11010111000101 9
b11000 1
b1111101101101011110101101000 .
b10010010100100 6
b11111111111111110100111111100111 7
b11000 0
b11000 8
1&
#2250018
0&
#2291685
b1011111000111 +
b100110011101100000001101 "
b100110011101100000001101 /
b1001001001011 -
b10111110001111011 ,
b1010101011111010 *
b1010101011111010 9
b11001 1
b1111101100010010101000100110000 .
b10010010010111000 6
b10010010100100 7
b11001 0
b11001 8
1&
#2333352
0&
#2375019
b111011100100 +
b101100111011100001001111 "
b101100111011100001001111 /
b1011111000111 -
b1110111001001111 ,
b1000011001010101 *
b1000011001010101 9
b11010 1
b10100011001011001001100000001110 .
b10111110001111011 6
b10010010010111000 7
b11010 0
b11010 8
1&
#2416686
0&
#2458353
b100000010 +
b110001010000000010101110 "
b110001010000000010101110 /
b111011100100 -
b1000000101110 ,
b1111001111011011 *
b1111001111011011 9
b11011 1
b1100110001100111010110101010110 .
b1110111001001111 6
b10111110001111011 7
b11011 0
b11011 8
1&
#2500020
0&
#2541687
b1111111111111111111111111111111111111111111111111111100111010110 +
b1100011010101100001011 "
b1100011010101100001011 /
b100000010 -
b11111111111111111001110101101010 ,
b110111111111000 *
b110111111111000 9
b11100 1
b110111100000101101001001100 .
b1000000101110 6
b1110111001001111 7
b11100 0
b11100 8
1&
#2583354
0&
#2625021
b1111111111111111111111111111111111111111111111111111101011000100 +
b10100000101110010010 "
b10100000101110010010 /
b1111111111111111111111111111111111111111111111111111100111010110 -
b11111111111111111010110001000100 ,
b110010110010001 *
b110010110010001 9
b11101 1
b111111111111111111010101101110000101011110100100 .
b11111111111111111001110101101010 6
b1000000101110 7
b11101 0
b11101 8
1&
#2666688
0&
#2708355
b1111111111111111111111111111111111111111111111111111101101000001 +
b1110100111010101111 "
b1110100111010101111 /
b1111111111111111111111111111111111111111111111111111101011000100 -
b11111111111111111011010000010110 ,
b1110000100100101 *
b1110000100100101 9
b11110 1
b111111111111111111011100000101101110000110101000 .
b11111111111111111010110001000100 6
b11111111111111111001110101101010 7
b11110 0
b11110 8
1&
#2750022
0&
#2791689
b1111111111111111111111111111111111111111111111111111010100110100 +
b1100110011000101100101 "
b1100110011000101100101 /
b1111111111111111111111111111111111111111111111111111101101000001 -
b11111111111111110101001101001011 ,
b1000000111001010 *
b1000000111001010 9
b11111 1
b111111111111111111011111011100010111011101011100 .
b11111111111111111011010000010110 6
b11111111111111111010110001000100 7
b11111 0
b11111 8
1&
#2833356
0&
#2875023
b1111111111111111111111111111111111111111111111111110110111011011 +
b11011011011101101011000 "
b11011011011101101011000 /
b1111111111111111111111111111111111111111111111111111010100110100 -
b11111111111111101101110110110100 ,
b1011101000010000 *
b1011101000010000 9
b100000 1
b111111111111111110110101111011101010100000101110 .
b11111111111111110101001101001011 6
b11111111111111111011010000010110 7
b100000 0
b100000 8
1&
#2916690
0&
#2958357
b1111111111111111111111111111111111111111111111111111000000010001 +
b10101110010011100010011 "
b10101110010011100010011 /
b1111111111111111111111111111111111111111111111111110110111011011 -
b11111111111111110000000100010010 ,
b100011001011011 *
b100011001011011 9
b100001 1
b111111111111111110000011100000001001010000001000 .
b11111111111111101101110110110100 6
b11111111111111110101001101001011 7
b100001 0
b100001 8
1&
#3000024
0&
#3041691
b1111111111111111111111111111111111111111111111111111111010110001 +
b110110111101001011010111 "
b110110111101001011010111 /
b1111111111111111111111111111111111111111111111111111000000010001 -
b11111111111111111110101100011010 ,
b111111000100000 *
b111111000100000 9
b100010 1
b111111111111111110010010101010111000001000110100 .
b11111111111111110000000100010010 6
b11111111111111101101110110110100 7
b100010 0
b100010 8
1&
#3083358
0&
#3125025
b111110010111 +
b1000101111100000010010011 "
b1000101111100000010010011 /
b1111111111111111111111111111111111111111111111111111111010110001 -
b1111100101110010 ,
b1111001011110 *
b1111001011110 9
b100011 1
b111111111111111111110111000010011001010010000100 .
b11111111111111111110101100011010 6
b11111111111111110000000100010010 7
b100011 0
b100011 8
1&
#3166692
0&
#3208359
b1010110101111 +
b100001010101001010100010 "
b100001010101001010100010 /
b111110010111 -
b10101101011110000 ,
b1001101000100001 *
b1001101000100001 9
b100100 1
b1101010111110100101110111110100 .
b1111100101110010 6
b11111111111111111110101100011010 7
b100100 0
b100100 8
1&
#3250026
0&
#3291693
b111010011111 +
b100011000001011100111010 "
b100011000001011100111010 /
b1010110101111 -
b1110100111111011 ,
b1001000001000110 *
b1001000001000110 9
b100101 1
b10010100110010011111000101100000 .
b10101101011110000 6
b1111100101110010 7
b100101 0
b100101 8
1&
#3333360
0&
#3375027
b10000110001 +
b11111100011011101011001 "
b11111100011011101011001 /
b111010011111 -
b100001100010110 ,
b110010100101 *
b110010100101 9
b100110 1
b1100100010110000111111100001110 .
b1110100111111011 6
b10101101011110000 7
b100110 0
b100110 8
1&
#3416694
0&
#3458361
b101110 +
b100000100111011100110 "
b100000100111011100110 /
b10000110001 -
b1011101101 ,
b111100111010011 *
b111100111010011 9
b100111 1
b11100110001010100110101011100 .
b100001100010110 6
b1110100111111011 7
b100111 0
b100111 8
1&
#3500028
0&
#3541695
b101101001 +
b11001011000001111 "
b11001011000001111 /
b101110 -
b1011010010011 ,
b101010010100101 *
b101010010100101 9
b101000 1
b1010000010011100000000010 .
b1011101101 6
b100001100010110 7
b101000 0
b101000 8
1&
#3583362
0&
#3625029
b1111111111111111111111111111111111111111111111111111111011011001 +
b1100001101010100010 "
b1100001101010100010 /
b101101001 -
b11111111111111111110110110010010 ,
b1100100111000110 *
b1100100111000110 9
b101001 1
b1001101011100110011011111110 .
b1011010010011 6
b1011101101 7
b101001 0
b101001 8
1&
#3666696
0&
#3708363
b1111111111111111111111111111111111111111111111111111010010011101 +
b11011000111100111100001 "
b11011000111100111100001 /
b1111111111111111111111111111111111111111111111111111111011011001 -
b11111111111111110100100111011100 ,
b1000000000001101 *
b1000000000001101 9
b101010 1
b111111111111111111111000000110001001111100110100 .
b11111111111111111110110110010010 6
b1011010010011 7
b101010 0
b101010 8
1&
#3750030
0&
#3791697
b1111111111111111111111111111111111111111111111111110101010100000 +
b101010010000010110001111 "
b101010010000010110001111 /
b1111111111111111111111111111111111111111111111111111010010011101 -
b11111111111111101010101000000100 ,
b1101000000001011 *
b1101000000001011 9
b101011 1
b111111111111111110110001111000101111001110011000 .
b11111111111111110100100111011100 6
b11111111111111111110110110010010 7
b101011 0
b101011 8
1&
#3833364
0&
#3875031
b1111111111111111111111111111111111111111111111111110110001010010 +
b11110101001000110111100 "
b11110101001000110111100 /
b1111111111111111111111111111111111111111111111111110101010100000 -
b11111111111111101100010100100001 ,
b101100110100110 *
b101100110100110 9
b101100 1
b111111111111111101101101010101011101101100101000 .
b11111111111111101010101000000100 6
b11111111111111110100100111011100 7
b101100 0
b101100 8
1&
#3916698
0&
#3958365
b1111111111111111111111111111111111111111111111111111101100010110 +
b111101011000101010010101 "
b111101011000101010010101 /
b1111111111111111111111111111111111111111111111111110110001010010 -
b11111111111111111011000101100100 ,
b111011110001110 *
b111011110001110 9
b101101 1
b111111111111111101111000111101101001100100001010 .
b11111111111111101100010100100001 6
b11111111111111101010101000000100 7
b101101 0
b101101 8
1&
